Verilog-154-233/Dataflow/VerilogDM-154-233.v
`timescale 1ns/100ps

/*
        TITLE: THE MODIFIED ENIGMA MACHINE

        REG NO: 16CO154-16CO233

        ABSTRACT: A circuit that encrypts data by mapping each alphabet to another alphabet randomly.
                  Thus a message is encrypted by a user based on a setting decided by the user and the receiver.
                  The receiver has to enter the encrypted data along with the same decided setting to get the desired (decrypted) message.

        FUNCTIONALITIES: The following modules are present:

                            1) VerilogDM_154_233: Handles the selection of black box modules as per the setting along with passing inputs and outputs
                            2) block1, block2, block3, block4 : These are black boxes in which an alphabet is mapped to another alphabet.  
                            3) encoder : An alphabet is converted to its 5-bit binary enquivalent from a => 00000 to z => 11001.
                            4) decoder : 5-bit binary is converted to its enquivalent alphabet character from 00000 => a to 11001 => z.

        BRIEF DESCRIPTION OF CODE:  The user enters the characters of the message in the test bench
                                    along with the setting code for each character which the user has decided and has passed to the receiver.
                                    This data is then encrypted in the following module and then displayed.
                                    The encoder module converts the input ASCII character to 5 bit equivalent.
                                    Each black box gives the corresponding output based on the mapping done inside it,
                                    The VerilogDM_154_233 module handles the selection of the black box outputs based on the setting input.
                                    It then puts the selected answer from the black box to the decoder.
                                    The decoder module converts the 5 bit encoding to its ASCII equivalent.
                                    Through the VerilogDM_154_233 the decoded output is fed to the output of the machine.
                                    For decrypting the same set of character produced during encoding must be entered with same settings.
        
        MODEL: Data Flow                            
*/


/**
 * Main Module for MODIFIED ENIGMA MACHINE 
 */ 
module VerilogDM_154_233 (output [8:1] out,  // output: output character of the machine
                          input [8:1] in,        // input: input character to the machine,
                          input [1:0] setting);  // input: setting given to the machine


    // Variables for outputs from each black box module
        // variable to store output from black box 1
    wire [4:0] out1;

        // variable to store output from black box 2
    wire [4:0] out2;

        // variable to store output from black box 3
    wire [4:0] out3;

        // variable to store output from black box 4
    wire [4:0] out4;



    // Varible to get 5 bit binary encoding for the 8 bit ASCII character
    wire [4:0] encodedInput;



    // Variable to select the bits from all black boxes based on setting
    wire [4:0] selectedOut;



    // Encoder module thread instantiated
    // (output: stored in encodedInput variable after converting to 5 bit encoding from 8 bit ASCII, input: input to machine (character in ASCII))
    encoder Encoder (encodedInput, in);



    // Black box threads instantiated 
        // black box 1 (output: output bits from box1, input: encodedInput bits from encoder module)
    block1 box1 (out1, encodedInput);
    
        // black box 2 (output: output bits from box2, input: encodedInput bits from encoder module)
    block2 box2 (out2, encodedInput);

        // black box 3 (output: output bits from box3, input: encodedInput bits from encoder module)
    block3 box3 (out3, encodedInput);

        // black box 4 (output: output bits from box4, input: encodedInput bits from encoder module)
    block4 box4 (out4, encodedInput);



    // Selection logic

    // selectedOut[] is the array having the desired result. It must be given a value according to the settings and out variable.
    // So boolean funcition for getting the out bits from a particular black box for a particular setting was found out
    // This is done such that if setting were 0 then the selectedOut will be equivalent to out1 and so on.
    assign selectedOut[0] = (~setting[0] & ~setting[1] & out1[0]) | (setting[0] & ~setting[1] & out2[0]) | (~setting[0] & setting[1] & out3[0]) | (setting[0] & setting[1] & out4[0]);
    assign selectedOut[1] = (~setting[0] & ~setting[1] & out1[1]) | (setting[0] & ~setting[1] & out2[1]) | (~setting[0] & setting[1] & out3[1]) | (setting[0] & setting[1] & out4[1]);
    assign selectedOut[2] = (~setting[0] & ~setting[1] & out1[2]) | (setting[0] & ~setting[1] & out2[2]) | (~setting[0] & setting[1] & out3[2]) | (setting[0] & setting[1] & out4[2]);
    assign selectedOut[3] = (~setting[0] & ~setting[1] & out1[3]) | (setting[0] & ~setting[1] & out2[3]) | (~setting[0] & setting[1] & out3[3]) | (setting[0] & setting[1] & out4[3]);
    assign selectedOut[4] = (~setting[0] & ~setting[1] & out1[4]) | (setting[0] & ~setting[1] & out2[4]) | (~setting[0] & setting[1] & out3[4]) | (setting[0] & setting[1] & out4[4]);
    


    // Decoder module thread instantiated 
    // (output: output of the machine, input: selected bits from selection logic)
    decoder Decoder (out, selectedOut);
    

endmodule



/**
 * Module depicting black box 1 functionality in circuit
 * (output: encoded character for the given input, input: input character to the black box)
 * output bits: (MSB)F1F2F3F4F5(LSB), input bits: (MSB)ABCDE(LSB)
 */
module block1 (output [4:0] out, input [4:0] in);

	// Each character bits is mapped to another character which is chosen for this block using boolean functions
	// The equation is reduced using K Map

    // F5 = D'CE' + AD'E' + ACD + A'C'DE' + A'B'C'D' + A'B'D'E 
    assign out[0] = (~in[1] & in[2] & ~in[0]) | (in[4] & ~in[1] & ~in[0]) | (in[4] & in[2] & in[1]) | (~in[4] & ~in[2] & in[1] & ~in[0]) | (~in[4] & in[3] & ~in[2] & ~in[1]) | (~in[4] & ~in[3] & ~in[1] & in[0]);
    
    // F4 = AE' + AB + B'D'E' + B'CE' + ACD' + A'B'C'E 
    assign out[1] = (in[4] & ~in[0]) | (in[4] & in[3]) | (~in[3] & ~in[1] & ~in[0]) | (~in[3] & in[2] & ~in[0]) | (in[4] & in[2] & ~in[1]) | (~in[4] & ~in[3] & ~in[2] & in[0]);
    
    // F3 = A'C'D' + AB'C' + A'B'DE + A'BC'E' + AB'D'E'
    assign out[2] = (~in[4] & ~in[2] & ~in[1]) | (in[4] & ~in[3] & ~in[2]) | (~in[4] & ~in[3] & in[1] & in[0]) | (~in[4] & in[3] & ~in[2] & ~in[0]) | (in[4] & ~in[3] & ~in[1] & ~in[0]);
    
    // F2 = C'D'E' + CD'E + A'B'C'E' + AB'C'D' + BC'DE;
    assign out[3] = (~in[2] & ~in[1] & ~in[0]) | (in[2] & ~in[1] & in[0]) | (~in[4] & ~in[3] & ~in[2] & ~in[0]) | (in[4] & ~in[3] & ~in[2] & ~in[1]) | (in[3] & ~in[2] & in[1] & in[0]);
    
    // F1 = A'B'D + A'C'D + A'DE + A'B'C'E + A'CD'E'
    assign out[4] = (~in[4] & ~in[3] & in[1]) | (~in[4] & ~in[2] & in[1]) | (~in[4] & in[1] & in[0]) | (~in[4] & ~in[3] & ~in[2] & in[0]) | (~in[4] & in[2] & ~in[1] & ~in[0]);

endmodule



/**
 * Module depicting black box 2 functionality in circuit
 * (output: encoded character for the given input, input: input character to the black box)
 * output bits: (MSB)F1F2F3F4F5(LSB), input bits: (MSB)ABCDE(LSB)
 */
module block2 (output [4:0] out, input [4:0] in);

	// Each character bits is mapped to another character which is chosen for this block using boolean functions
	// The equation is reduced using K Map


    // F5 = A'D'E + A'CE + BCD' + ACD' + A'B'C'E' + B'C'D'E' + AC'DE 
    assign out[0] = (~in[4] & ~in[1] & in[0]) | (~in[4] & in[2] & in[0]) | (in[3] & in[2] & ~in[1]) | (in[4] & in[2] & ~in[1]) | (~in[4] & ~in[3] & ~in[2] & ~in[0]) | (~in[3] & ~in[2] & ~in[1] & ~in[0]) | (in[4] & ~in[2] & in[1] & in[0]);
    
    // F4 = A'DE' + CDE' + B'C'D'E' + A'B'C'D + A'B'CD' + A'BD'E
    assign out[1] = (~in[4] & in[1] & ~in[0]) | (in[2] & in[1] & ~in[0]) | (~in[3] & ~in[2] & ~in[1] & ~in[0]) | (~in[4] & ~in[3] & ~in[2] & in[1]) | (~in[4] & ~in[3] & in[2] & ~in[1]) | (~in[4] & in[3] & ~in[1] & in[0]);
    
    // F3 = A'CE + A'CD + BDE' + AC'D'E + A'B'C'D' + AC'DE'
    assign out[2] = (~in[4] & in[2] & in[0]) | (~in[4] & in[2] & in[1]) | (in[3] & in[1] & ~in[0]) | (in[4] & ~in[2] & ~in[1] & in[0]) | (~in[4] & ~in[3] & ~in[2] & ~in[1]) | (in[4] & ~in[2] & in[1] & ~in[0]);
    
    // F2 = BCE + AD'E' + B'CDE' + BC'D'E' + AB'C'E
    assign out[3] = (in[3] & in[2] & in[0]) | (in[4] & ~in[1] & ~in[0]) | (~in[3] & in[2] & in[1] & ~in[0]) | (in[3] & ~in[2] & ~in[1] & ~in[0]) | (in[4] & ~in[3] & ~in[2] & in[0]);
    
    // F1 = A'C'D' + A'BC' + CD'E' + BC'E
    assign out[4] = (~in[4] & ~in[2] & ~in[1]) | (~in[4] & in[3] & ~in[2]) | (in[2] & ~in[1] & ~in[0]) | (in[3] & ~in[2] & in[0]);

endmodule



/**
 * Module depicting black box 3 functionality in circuit
 * (output: encoded character for the given input, input: input character to the black box)
 * output bits: (MSB)F1F2F3F4F5(LSB), input bits: (MSB)ABCDE(LSB)
 */
module block3 (output [4:0] out, input [4:0] in);

	// Each character bits is mapped to another character which is chosen for this block using boolean functions
	// The equation is reduced using K Map


    // F5 = A'B'C' + B'CD' + C'DE + CD'E' + ADE'
    assign out[0] = (~in[4] & ~in[3] & ~in[2]) | ( ~in[3] & in[2] & ~in[1]) | (~in[2] & in[1] & in[0]) | ( in[2] & ~in[1] & ~in[0]) | ( in[4] & in[1] & ~in[0]);
    
    // F4 = CD + A'B'D + A'DE + A'B'CE + AB'C'E' 
    assign out[1] = (in[2] & in[1]) | (~in[4] & ~in[3] & in[1]) | (~in[4] & in[1] & in[0]) | (~in[4] & ~in[3] & in[2] & in[0]) | (in[4] & ~in[3] & ~in[2] & ~in[0]);
    
    // F3 = B'DE' + BD'E + BCD + ACE' + AC'D + A'C'D'E  
    assign out[2] = (~in[3] & in[1] & ~in[0]) | (in[3] & ~in[1] & in[0]) | (in[3] & in[2] & in[1]) | (in[4] & in[2] & ~in[0]) | (in[4] & ~in[2] & in[1]) | (~in[4] & ~in[2] & ~in[1] & in[0]);
    
    // F2 = AB + B'CE' + BD'E' + AD'E' + A'B'C'DE 
    assign out[3] = (in[4] & in[3]) | (~in[3] & in[2] & ~in[0]) | (in[3] & ~in[1] & ~in[0]) | (in[4] & ~in[1] & ~in[0]) | (~in[4] & ~in[3] & ~in[2] & in[1] & in[0]);
    
    // F1 = BCD' + BCE + A'B'C'D' + A'B'D'E + A'BC'E' + AC'DE' + ACDE 
    assign out[4] = (in[3] & in[2] & ~in[1]) | (in[3] & in[2] & in[0]) | (~in[4] & ~in[3] & ~in[2] & ~in[1]) | (~in[4] & ~in[3] & ~in[1] & in[0]) | (~in[4] & in[3] & ~in[2] & ~in[0]) | (in[4] & ~in[2] & in[1] & ~in[0]) | (in[4] & in[2] & in[1] & in[0]);
    

endmodule



/**
 * Module depicting black box 4 functionality in circuit
 * (output: encoded character for the given input, input: input character to the black box)
 * output bits: (MSB)F1F2F3F4F5(LSB), input bits: (MSB)ABCDE(LSB)
 */
module block4 (output [4:0] out, input [4:0] in);

	// Each character bits is mapped to another character which is chosen for this block using boolean functions
	// The equation is reduced using K Map


    // F5 = AE' + B'D'E' + CDE' + BC'E' + A'B'CD + AB'C'D'
    assign out[0] = (in[4] & ~in[0]) | (~in[3] & ~in[1] & ~in[0]) | (in[2] & in[1] & ~in[0]) | (in[3] & ~in[2] & ~in[0]) | (~in[4] & ~in[3] & in[2] & in[1]) | (in[4] & ~in[3] & ~in[2] & ~in[1]);
    
    // F4 = AB'C' + BDE' + BCD' + AC'E + ADE + B'C'DE + AB'D'E' 
    assign out[1] = (in[4] & ~in[3] & ~in[2]) | ( in[3] & in[1] & ~in[0]) | (in[3] & in[2] & ~in[1]) | (in[4] & ~in[2] & in[0]) | (in[4] & in[1] & in[0]) | (~in[3] & ~in[2] & in[1] & in[0]) | (in[4] & ~in[3] & ~in[1] & ~in[0]);
    
    // F3 = BD'E + BCD + A'C'D'E' + A'B'DE' + AC'D'E + ACD'E' + ACDE
    assign out[2] = (in[3] & ~in[1] & in[0]) | (in[3] & in[2] & in[1]) | (~in[4] & ~in[2] & ~in[1] & ~in[0]) | (~in[4] & ~in[3] & in[1] & ~in[0]) | (in[4] & ~in[2] & ~in[1] & in[0]) | (in[4] & in[2] & ~in[1] & ~in[0]) | (in[4] & in[2] & in[1] & in[0]);
    
    // F2 = AC + B'CE' + ADE + A'B'DE' + AB'D'E' + A'B'C'D'E
    assign out[3] = (in[4] & in[2]) | (~in[3] & in[2] & ~in[0]) | (in[4] & in[1] & in[0]) | (~in[4] & ~in[3] & in[1] & ~in[0]) | (in[4] & ~in[3] & ~in[1] & ~in[0]) | (~in[4] & ~in[3] & ~in[2] & ~in[1] & in[0]);
    
    // F1 = BD + A'DE + ABE + A'B'C'E + A'BC'E' + ACDE' 
    assign out[4] = (in[3] & in[1]) | (~in[4] & in[1] & in[0]) | (in[4] & in[3] & in[0]) | (~in[4] & ~in[3] & ~in[2] & in[0]) | (~in[4] & in[3] & ~in[2] & ~in[0]) | (in[4] & in[2] & in[1] & ~in[0]);

endmodule



/**
 * Module for Encoder
 * (output: stored in encodedInput variable after converting to 5 bit encoding from 8 bit ASCII, input: input to machine (character in ASCII))
 * Converts 8 bit ASCII character to 5 bit equivalent
 * eg. A => '00000' to Z => '11001'
 */
module encoder (output [4:0] encodedInput, input [8:1] in);

    // variable for the conversion
    wire [8:1] res;
    
    // substact the ASCII value of "A" to get the correspoding bits
    assign res = in - "A";

    // first 5 bits will be the 5 bit encoding needed for this circuit
    assign encodedInput[4] = res[5];
    assign encodedInput[3] = res[4];
    assign encodedInput[2] = res[3];
    assign encodedInput[1] = res[2];
    assign encodedInput[0] = res[1];

endmodule



/**
 * Module for Decoder
 * (output: output of the machine, input: selected bits from selection logic)
 * Converts 5 bit character encoding to its 8 bit ASCII equivalent
 * eg. '00000' => A to '11001' => Z
 */
module decoder (output [8:1] out, input [4:0] selectedOut);

    // variable for the conversion
    wire [8:1] res;

    // feed the 5 bit to the 8 bit variable
    assign res[8] = 1'b0;
    assign res[7] = 1'b0;
    assign res[6] = 1'b0;
    assign res[5] = selectedOut[4];
    assign res[4] = selectedOut[3];
    assign res[3] = selectedOut[2];
    assign res[2] = selectedOut[1];
    assign res[1] = selectedOut[0];

    // offset by ASCII character "A" to get final ASCII character value
    assign out = res + "A";

endmodule

Verilog-154-233/Dataflow/Verilog-154-233.v
    `timescale 1ns/100ps

// TEST BENCH

/*
        TITLE: THE MODIFIED ENIGMA MACHINE

        REG NO: 16CO154-16CO233

        ABSTRACT: A circuit that encrypts data by mapping each alphabet to another alphabet randomly.
                  Thus a message is encrypted by a user based on a setting decided by the user and the receiver.
                  The receiver has to enter the encrypted data along with the same decided setting to get the desired (decrypted) message.

        FUNCTIONALITIES: The following modules are present

                            1) Verilog_154_233: It provides the stimulus for the VerilogBM_102_205, VerilogDM_102_205 modules to run
                                                Providing the input to the machine and the setting decided by sender and receiver

        BRIEF DESCRIPTION OF CODE:  The user enters the characters of the message in the test bench
                                    along with the setting code for each character which the user has decided and has passed to the receiver.
                                    This data is then encrypted in VerilogBM_102_205, VerilogDM_102_205 modules and then displayed.
                                    Each black box inside the main modules gives the corresponding output based on the mapping done inside it,
                                    The VerilogBM_102_205, VerilogDM_102_205 module handles the selection of the black box outputs based on the setting input.
                                    It then puts the selected answer from the black box to the output of the machine.
                                    For decrypting the same set of character produced during encoding must be entered with same settings.
*/



module Verilog_154_233;

    reg [1:0] setting;
    reg [8:1] in;
    wire [8:1] out;

    // Main Module for MODIFIED ENIGMA MACHINE instantiated
    VerilogDM_154_233 inst(out, in, setting);
    
	// input combinations 
    initial begin

        $dumpfile("VerilogDM-154-233.vcd");
        $dumpvars(0, Verilog_154_233);

        $display("\n\n ================== THE MODIFIED ENIGMA MACHINE ==================\n");
        $display("\n\t------ ENCRYPTING: \"HELLOWORLD\", SETTINGS: 2103 ------\n");

        setting = 2'b10;
        in = "H";
        #10;
        setting = 2'b01;
        in = "E";
        #10;
        setting = 2'b00;
        in = "L";
        #10;
        setting = 2'b11;
        in = "L";
        #10;
        setting = 2'b10;
        in = "O";
        #10;
        setting = 2'b01;
        in = "W";
        #10;
        setting = 2'b00;
        in = "O";
        #10;
        setting = 2'b11;
        in = "R";
        #10;
        setting = 2'b10;
        in = "L";
        #10;
        setting = 2'b01;
        in = "D";
        #10;

        $display("\n\t------ DECRYPTING: \"CSYQGKAHDC\", SETTINGS: 2103 ------\n");

        #10;
        setting = 2'b10;
        in = "C";
        #10;
        setting = 2'b01;
        in = "S";
        #10;
        setting = 2'b00;
        in = "Y";
        #10;
        setting = 2'b11;
        in = "Q";
        #10;
        setting = 2'b10;
        in = "G";
        #10;
        setting = 2'b01;
        in = "K";
        #10;
        setting = 2'b00;
        in = "A";
        #10;
        setting = 2'b11;
        in = "H";
        #10;
        setting = 2'b10;
        in = "D";
        #10;
        setting = 2'b01;
        in = "C";
        #10;
    end

	// display outputs
    always @ (setting) begin
        #5;
        $display("\n\t\tinput: %c output: %c\n", in, out);
    end

endmodule

Verilog-154-233/Dataflow/VerilogDM-154-233.vcd
$date
	Tue Nov 07 21:19:16 2017
$end
$version
	Icarus Verilog
$end
$timescale
	100ps
$end
$scope module Verilog_154_233 $end
$var wire 8 ! out [8:1] $end
$var reg 8 " in [8:1] $end
$var reg 2 # setting [1:0] $end
$scope module inst $end
$var wire 8 $ in [8:1] $end
$var wire 2 % setting [1:0] $end
$var wire 5 & selectedOut [4:0] $end
$var wire 5 ' out4 [4:0] $end
$var wire 5 ( out3 [4:0] $end
$var wire 5 ) out2 [4:0] $end
$var wire 5 * out1 [4:0] $end
$var wire 8 + out [8:1] $end
$var wire 5 , encodedInput [4:0] $end
$scope module Decoder $end
$var wire 5 - selectedOut [4:0] $end
$var wire 8 . res [8:1] $end
$var wire 8 / out [8:1] $end
$upscope $end
$scope module Encoder $end
$var wire 8 0 in [8:1] $end
$var wire 8 1 res [8:1] $end
$var wire 5 2 encodedInput [4:0] $end
$upscope $end
$scope module box1 $end
$var wire 5 3 in [4:0] $end
$var wire 5 4 out [4:0] $end
$upscope $end
$scope module box2 $end
$var wire 5 5 in [4:0] $end
$var wire 5 6 out [4:0] $end
$upscope $end
$scope module box3 $end
$var wire 5 7 in [4:0] $end
$var wire 5 8 out [4:0] $end
$upscope $end
$scope module box4 $end
$var wire 5 9 in [4:0] $end
$var wire 5 : out [4:0] $end
$upscope $end
$upscope $end
$upscope $end
$enddefinitions $end
#0
$dumpvars
b10001 :
b111 9
b10 8
b111 7
b101 6
b111 5
b10100 4
b111 3
b111 2
b111 1
b1001000 0
b1000011 /
b10 .
b10 -
b111 ,
b1000011 +
b10100 *
b101 )
b10 (
b10001 '
b10 &
b10 %
b1001000 $
b10 #
b1001000 "
b1000011 !
$end
#100
b1001 (
b1001 8
b10010 )
b10010 6
b10011 *
b10011 4
b1010011 !
b1010011 +
b1010011 /
b10010 .
b1001 '
b1001 :
b10010 &
b10010 -
b100 ,
b100 2
b100 3
b100 5
b100 7
b100 9
b100 1
b1000101 "
b1000101 $
b1000101 0
b1 #
b1 %
#200
b10000 '
b10000 :
b1011001 !
b1011001 +
b1011001 /
b11000 .
b10000 )
b10000 6
b11000 &
b11000 -
b11000 *
b11000 4
b11 (
b11 8
b1011 ,
b1011 2
b1011 3
b1011 5
b1011 7
b1011 9
b1011 1
b1001100 "
b1001100 $
b1001100 0
b0 #
b0 %
#300
b1010001 !
b1010001 +
b1010001 /
b10000 .
b10000 &
b10000 -
b11 #
b11 %
#400
b110 )
b110 6
b10111 '
b10111 :
b110 (
b110 8
b1000111 !
b1000111 +
b1000111 /
b110 .
b0 *
b0 4
b110 &
b110 -
b1110 ,
b1110 2
b1110 3
b1110 5
b1110 7
b1110 9
b1110 1
b1001111 "
b1001111 $
b1001111 0
b10 #
b10 %
#500
b1010 )
b1010 6
b11001 '
b11001 :
b11 *
b11 4
b1001011 !
b1001011 +
b1001011 /
b1010 .
b1111 (
b1111 8
b1010 &
b1010 -
b10110 ,
b10110 2
b10110 3
b10110 5
b10110 7
b10110 9
b10110 1
b1010111 "
b1010111 $
b1010111 0
b1 #
b1 %
#600
b0 *
b0 4
b110 )
b110 6
b1000001 !
b1000001 +
b1000001 /
b0 .
b10111 '
b10111 :
b0 &
b0 -
b110 (
b110 8
b1110 ,
b1110 2
b1110 3
b1110 5
b1110 7
b1110 9
b1110 1
b1001111 "
b1001111 $
b1001111 0
b0 #
b0 %
#700
b111 '
b111 :
b0 (
b0 8
b1100 )
b1100 6
b1100 *
b1100 4
b1001000 !
b1001000 +
b1001000 /
b111 .
b111 &
b111 -
b10001 ,
b10001 2
b10001 3
b10001 5
b10001 7
b10001 9
b10001 1
b1010010 "
b1010010 $
b1010010 0
b11 #
b11 %
#800
b11000 *
b11000 4
b10000 )
b10000 6
b11 (
b11 8
b10000 '
b10000 :
b1000100 !
b1000100 +
b1000100 /
b11 .
b11 &
b11 -
b1011 ,
b1011 2
b1011 3
b1011 5
b1011 7
b1011 9
b1011 1
b1001100 "
b1001100 $
b1001100 0
b10 #
b10 %
#900
b1011 (
b1011 8
b10010 '
b10010 :
b10 )
b10 6
b10110 *
b10110 4
b1000011 !
b1000011 +
b1000011 /
b10 .
b10 &
b10 -
b11 ,
b11 2
b11 3
b11 5
b11 7
b11 9
b11 1
b1000100 "
b1000100 $
b1000100 0
b1 #
b1 %
#1100
b11 )
b11 6
b1001000 !
b1001000 +
b1001000 /
b111 .
b111 &
b111 -
b1100 '
b1100 :
b11001 *
b11001 4
b111 (
b111 8
b10 ,
b10 2
b10 3
b10 5
b10 7
b10 9
b10 1
b1000011 "
b1000011 $
b1000011 0
b10 #
b10 %
#1200
b110 *
b110 4
b11 '
b11 :
b10111 (
b10111 8
b100 )
b100 6
b1000101 !
b1000101 +
b1000101 /
b100 .
b100 &
b100 -
b10010 ,
b10010 2
b10010 3
b10010 5
b10010 7
b10010 9
b10010 1
b1010011 "
b1010011 $
b1010011 0
b1 #
b1 %
#1300
b1 '
b1 :
b1001100 !
b1001100 +
b1001100 /
b1011 .
b1011 *
b1011 4
b1011 &
b1011 -
b1000 )
b1000 6
b1000 (
b1000 8
b11000 ,
b11000 2
b11000 3
b11000 5
b11000 7
b11000 9
b11000 1
b1011001 "
b1011001 $
b1011001 0
b0 #
b0 %
#1400
b1011 )
b1011 6
b1001100 !
b1001100 +
b1001100 /
b1011 .
b1111 *
b1111 4
b1010 (
b1010 8
b1011 '
b1011 :
b1011 &
b1011 -
b10000 ,
b10000 2
b10000 3
b10000 5
b10000 7
b10000 9
b10000 1
b1010001 "
b1010001 $
b1010001 0
b11 #
b11 %
#1500
b10010 *
b10010 4
b1101 '
b1101 :
b1110 )
b1110 6
b1110 (
b1110 8
b1001111 !
b1001111 +
b1001111 /
b1110 .
b1110 &
b1110 -
b110 ,
b110 2
b110 3
b110 5
b110 7
b110 9
b110 1
b1000111 "
b1000111 $
b1000111 0
b10 #
b10 %
#1600
b10000 (
b10000 8
b10101 *
b10101 4
b10110 )
b10110 6
b10011 '
b10011 :
b1010111 !
b1010111 +
b1010111 /
b10110 .
b10110 &
b10110 -
b1010 ,
b1010 2
b1010 3
b1010 5
b1010 7
b1010 9
b1010 1
b1001011 "
b1001011 $
b1001011 0
b1 #
b1 %
#1700
b10111 )
b10111 6
b10001 (
b10001 8
b101 '
b101 :
b1110 *
b1110 4
b1001111 !
b1001111 +
b1001111 /
b1110 .
b1110 &
b1110 -
b0 ,
b0 2
b0 3
b0 5
b0 7
b0 9
b0 1
b1000001 "
b1000001 $
b1000001 0
b0 #
b0 %
#1800
b101 )
b101 6
b1010010 !
b1010010 +
b1010010 /
b10001 .
b10100 *
b10100 4
b10 (
b10 8
b10001 '
b10001 :
b10001 &
b10001 -
b111 ,
b111 2
b111 3
b111 5
b111 7
b111 9
b111 1
b1001000 "
b1001000 $
b1001000 0
b11 #
b11 %
#1900
b10 )
b10 6
b1011 (
b1011 8
b10110 *
b10110 4
b10010 '
b10010 :
b1001100 !
b1001100 +
b1001100 /
b1011 .
b1011 &
b1011 -
b11 ,
b11 2
b11 3
b11 5
b11 7
b11 9
b11 1
b1000100 "
b1000100 $
b1000100 0
b10 #
b10 %
#2000
b11 )
b11 6
b1000100 !
b1000100 +
b1000100 /
b11 .
b1100 '
b1100 :
b11 &
b11 -
b11001 *
b11001 4
b111 (
b111 8
b10 ,
b10 2
b10 3
b10 5
b10 7
b10 9
b10 1
b1000011 "
b1000011 $
b1000011 0
b1 #
b1 %
