Verilog/Behavioral/MEMB.v
`timescale 1ns/100ps

module MEM (output reg [8:1] out, input [8:1] in, input [1:0] setting);

    wire [8:1] out1;
    wire [8:1] out2;
    wire [8:1] out3;
    wire [8:1] out4;

    reg [8:1] inp;

    block1 box1 (out1, inp);
    block2 box2 (out2, inp);
    block3 box3 (out3, inp);
    block4 box4 (out4, inp);
    
    always @ (1) begin
        
        inp = in;
        #1;
        case (setting)
            2'b00: begin out = out1; end
            2'b01: begin out = out2; end
            2'b10: begin out = out3; end
            2'b11: begin out = out4; end
        endcase
    end

endmodule

module block1 (output reg [8:1] out, input [8:1] in);

    always @ (in) begin
        case (in)
            "A": begin out <= "B"; end
            "B": begin out <= "B"; end
            "C": begin out <= "B"; end
            "D": begin out <= "B"; end
            "E": begin out <= "B"; end
            "F": begin out <= "B"; end
            "G": begin out <= "B"; end
            "H": begin out <= "B"; end
            "I": begin out <= "B"; end
            "J": begin out <= "B"; end
            "K": begin out <= "B"; end
            "L": begin out <= "B"; end
            "M": begin out <= "B"; end
            "N": begin out <= "B"; end
            "O": begin out <= "B"; end
            "P": begin out <= "B"; end
            "Q": begin out <= "B"; end
            "R": begin out <= "B"; end
            "S": begin out <= "B"; end
            "T": begin out <= "B"; end
            "U": begin out <= "B"; end
            "V": begin out <= "B"; end
            "W": begin out <= "B"; end
            "X": begin out <= "B"; end
            "Y": begin out <= "B"; end
            "Z": begin out <= "B"; end
        endcase
    end

endmodule


module block2 (output reg [8:1] out, input [8:1] in);

    always @ (in) begin
        case (in)
            "A": begin out <= "B"; end
            "B": begin out <= "B"; end
            "C": begin out <= "B"; end
            "D": begin out <= "B"; end
            "E": begin out <= "B"; end
            "F": begin out <= "B"; end
            "G": begin out <= "B"; end
            "H": begin out <= "B"; end
            "I": begin out <= "B"; end
            "J": begin out <= "B"; end
            "K": begin out <= "B"; end
            "L": begin out <= "B"; end
            "M": begin out <= "B"; end
            "N": begin out <= "B"; end
            "O": begin out <= "B"; end
            "P": begin out <= "B"; end
            "Q": begin out <= "B"; end
            "R": begin out <= "B"; end
            "S": begin out <= "B"; end
            "T": begin out <= "B"; end
            "U": begin out <= "B"; end
            "V": begin out <= "B"; end
            "W": begin out <= "B"; end
            "X": begin out <= "B"; end
            "Y": begin out <= "B"; end
            "Z": begin out <= "B"; end
        endcase
    end

endmodule

module block3 (output reg [8:1] out, input [8:1] in);

    always @ (in) begin
        case (in)
            "A": begin out <= "B"; end
            "B": begin out <= "B"; end
            "C": begin out <= "B"; end
            "D": begin out <= "B"; end
            "E": begin out <= "B"; end
            "F": begin out <= "B"; end
            "G": begin out <= "B"; end
            "H": begin out <= "B"; end
            "I": begin out <= "B"; end
            "J": begin out <= "B"; end
            "K": begin out <= "B"; end
            "L": begin out <= "B"; end
            "M": begin out <= "B"; end
            "N": begin out <= "B"; end
            "O": begin out <= "B"; end
            "P": begin out <= "B"; end
            "Q": begin out <= "B"; end
            "R": begin out <= "B"; end
            "S": begin out <= "B"; end
            "T": begin out <= "B"; end
            "U": begin out <= "B"; end
            "V": begin out <= "B"; end
            "W": begin out <= "B"; end
            "X": begin out <= "B"; end
            "Y": begin out <= "B"; end
            "Z": begin out <= "B"; end
        endcase
    end

endmodule

module block4 (output reg [8:1] out, input [8:1] in);

    always @ (in) begin
        case (in)
            "A": begin out <= "B"; end
            "B": begin out <= "B"; end
            "C": begin out <= "B"; end
            "D": begin out <= "B"; end
            "E": begin out <= "B"; end
            "F": begin out <= "B"; end
            "G": begin out <= "B"; end
            "H": begin out <= "B"; end
            "I": begin out <= "B"; end
            "J": begin out <= "B"; end
            "K": begin out <= "B"; end
            "L": begin out <= "B"; end
            "M": begin out <= "B"; end
            "N": begin out <= "B"; end
            "O": begin out <= "B"; end
            "P": begin out <= "B"; end
            "Q": begin out <= "B"; end
            "R": begin out <= "B"; end
            "S": begin out <= "B"; end
            "T": begin out <= "B"; end
            "U": begin out <= "B"; end
            "V": begin out <= "B"; end
            "W": begin out <= "B"; end
            "X": begin out <= "B"; end
            "Y": begin out <= "B"; end
            "Z": begin out <= "B"; end
        endcase
    end

endmodule

Verilog/Behavioral/MEM.v
`timescale 1ns/100ps

/*
        TITLE: THE MODIFIED ENIGMA MACHINE

        REG NO: 16CO154-16CO233

        ABSTRACT: A circuit that encrypts data by mapping each alphabet to another alphabet randomly. 
                  This will be done in such a way that if the same alphabet is repeated, 
                  the encrypted alphabet will not be the same always.

        FUNCTIONALITIES: The following modules are present

                            a) Encoder: It is an alphabet to binary encoder
                            b) Decoder: It is a binary to alphabet decoder
                            
                            There is an input array- setting, which helps in deciding which block must encode/decode data
                            
                            c) Block 1,2,3 and 4: Blocks which encode/decode data using boolean equations

        BRIEF DESCRIPTION OF CODE:  The user enters some data (given in test-bench) and sets a code to encrypt the data.
                                    This data is then encrypted in the following module and then displayed.
                                    For decrypting the same data must be entered with same settings.
                                    For making the process easier there is an alphabet-binary encoder along with a binary-alphabet decoder.
*/

module t_MEM;

    reg [1:0] setting;
    reg [8:1] in;
    wire [8:1] out;

    
    MEM inst(out, in, setting);

    initial begin

        $dumpfile("MEM.vcd");
        $dumpvars(0, t_MEM);

        $display("\n\n ================== THE MODIFIED ENIGMA MACHINE ==================\n");
        $display("\n\t------ ENCRYPTING: \"HELLOWORLD\", SETTINGS: 2103 ------\n");

        setting = 2'b10;
        in = "H";
        #10;
        setting = 2'b01;
        in = "E";
        #10;
        setting = 2'b00;
        in = "L";
        #10;
        setting = 2'b11;
        in = "L";
        #10;
        setting = 2'b10;
        in = "O";
        #10;
        setting = 2'b01;
        in = "W";
        #10;
        setting = 2'b00;
        in = "O";
        #10;
        setting = 2'b11;
        in = "R";
        #10;
        setting = 2'b10;
        in = "L";
        #10;
        setting = 2'b01;
        in = "D";
        #10;

        $display("\n\t------ DECRYPTING: \"CSYQGKAHDC\", SETTINGS: 2103 ------\n");

        #10;
        setting = 2'b10;
        in = "C";
        #10;
        setting = 2'b01;
        in = "S";
        #10;
        setting = 2'b00;
        in = "Y";
        #10;
        setting = 2'b11;
        in = "Q";
        #10;
        setting = 2'b10;
        in = "G";
        #10;
        setting = 2'b01;
        in = "K";
        #10;
        setting = 2'b00;
        in = "A";
        #10;
        setting = 2'b11;
        in = "H";
        #10;
        setting = 2'b10;
        in = "D";
        #10;
        setting = 2'b01;
        in = "C";
        #10;
    end

    always @ (in) begin
        #5;
        $display("\n\t\tinput: %c output: %c\n", in, out);
    end

endmodule

Verilog/Behavioral/MEM.vcd
$date
	Sun Nov 05 17:48:46 2017
$end
$version
	Icarus Verilog
$end
$timescale
	100ps
$end
$scope module t_MEM $end
$var wire 8 ! out [8:1] $end
$var reg 8 " in [8:1] $end
$var reg 2 # setting [1:0] $end
$scope module inst $end
$var wire 8 $ in [8:1] $end
$var wire 2 % setting [1:0] $end
$var wire 8 & out4 [8:1] $end
$var wire 8 ' out3 [8:1] $end
$var wire 8 ( out2 [8:1] $end
$var wire 8 ) out1 [8:1] $end
$var reg 8 * inp [8:1] $end
$var reg 8 + out [8:1] $end
$scope module box1 $end
$var wire 8 , in [8:1] $end
$var reg 8 - out [8:1] $end
$upscope $end
$scope module box2 $end
$var wire 8 . in [8:1] $end
$var reg 8 / out [8:1] $end
$upscope $end
$scope module box3 $end
$var wire 8 0 in [8:1] $end
$var reg 8 1 out [8:1] $end
$upscope $end
$scope module box4 $end
$var wire 8 2 in [8:1] $end
$var reg 8 3 out [8:1] $end
$upscope $end
$upscope $end
$upscope $end
$enddefinitions $end
#0
$dumpvars
b1010010 3
b1001000 2
b1000011 1
b1001000 0
b1000110 /
b1001000 .
b1010101 -
b1001000 ,
bx +
b1001000 *
b1010101 )
b1000110 (
b1000011 '
b1010010 &
b10 %
b1001000 $
b10 #
b1001000 "
bx !
$end
#10
b1000011 !
b1000011 +
#100
b1010100 )
b1010100 -
b1010011 (
b1010011 /
b1001010 '
b1001010 1
b1001010 &
b1001010 3
b1000101 *
b1000101 ,
b1000101 .
b1000101 0
b1000101 2
b1000101 "
b1000101 $
b1 #
b1 %
#110
b1010011 !
b1010011 +
#200
b1010001 &
b1010001 3
b1000100 '
b1000100 1
b1010001 (
b1010001 /
b1011001 )
b1011001 -
b1001100 *
b1001100 ,
b1001100 .
b1001100 0
b1001100 2
b1001100 "
b1001100 $
b0 #
b0 %
#210
b1011001 !
b1011001 +
#300
b11 #
b11 %
#400
b1000001 )
b1000001 -
b1000111 (
b1000111 /
b1000111 '
b1000111 1
b1011000 &
b1011000 3
b1001111 *
b1001111 ,
b1001111 .
b1001111 0
b1001111 2
b1001111 "
b1001111 $
b10 #
b10 %
#410
b1000111 !
b1000111 +
#500
b1011010 &
b1011010 3
b1010000 '
b1010000 1
b1001011 (
b1001011 /
b1000100 )
b1000100 -
b1010111 *
b1010111 ,
b1010111 .
b1010111 0
b1010111 2
b1010111 "
b1010111 $
b1 #
b1 %
#510
b1001011 !
b1001011 +
#600
b1000001 )
b1000001 -
b1000111 (
b1000111 /
b1000111 '
b1000111 1
b1011000 &
b1011000 3
b1001111 *
b1001111 ,
b1001111 .
b1001111 0
b1001111 2
b1001111 "
b1001111 $
b0 #
b0 %
#610
b1000001 !
b1000001 +
#700
b1001000 &
b1001000 3
b1000001 '
b1000001 1
b1001101 (
b1001101 /
b1001101 )
b1001101 -
b1010010 *
b1010010 ,
b1010010 .
b1010010 0
b1010010 2
b1010010 "
b1010010 $
b11 #
b11 %
#710
b1001000 !
b1001000 +
#800
b1011001 )
b1011001 -
b1010001 (
b1010001 /
b1000100 '
b1000100 1
b1010001 &
b1010001 3
b1001100 *
b1001100 ,
b1001100 .
b1001100 0
b1001100 2
b1001100 "
b1001100 $
b10 #
b10 %
#810
b1000100 !
b1000100 +
#900
b1010011 &
b1010011 3
b1001100 '
b1001100 1
b1000011 (
b1000011 /
b1010111 )
b1010111 -
b1000100 *
b1000100 ,
b1000100 .
b1000100 0
b1000100 2
b1000100 "
b1000100 $
b1 #
b1 %
#910
b1000011 !
b1000011 +
#1100
b1011010 )
b1011010 -
b1000100 (
b1000100 /
b1001000 '
b1001000 1
b1001101 &
b1001101 3
b1000011 *
b1000011 ,
b1000011 .
b1000011 0
b1000011 2
b1000011 "
b1000011 $
b10 #
b10 %
#1110
b1001000 !
b1001000 +
#1200
b1000100 &
b1000100 3
b1011000 '
b1011000 1
b1000101 (
b1000101 /
b1000111 )
b1000111 -
b1010011 *
b1010011 ,
b1010011 .
b1010011 0
b1010011 2
b1010011 "
b1010011 $
b1 #
b1 %
#1210
b1000101 !
b1000101 +
#1300
b1001100 )
b1001100 -
b1001001 (
b1001001 /
b1001001 '
b1001001 1
b1000010 &
b1000010 3
b1011001 *
b1011001 ,
b1011001 .
b1011001 0
b1011001 2
b1011001 "
b1011001 $
b0 #
b0 %
#1310
b1001100 !
b1001100 +
#1400
b1001100 &
b1001100 3
b1001011 '
b1001011 1
b1001100 (
b1001100 /
b1010000 )
b1010000 -
b1010001 *
b1010001 ,
b1010001 .
b1010001 0
b1010001 2
b1010001 "
b1010001 $
b11 #
b11 %
#1500
b1010011 )
b1010011 -
b1001111 (
b1001111 /
b1001111 '
b1001111 1
b1001110 &
b1001110 3
b1000111 *
b1000111 ,
b1000111 .
b1000111 0
b1000111 2
b1000111 "
b1000111 $
b10 #
b10 %
#1510
b1001111 !
b1001111 +
#1600
b1010100 &
b1010100 3
b1010001 '
b1010001 1
b1010111 (
b1010111 /
b1010110 )
b1010110 -
b1001011 *
b1001011 ,
b1001011 .
b1001011 0
b1001011 2
b1001011 "
b1001011 $
b1 #
b1 %
#1610
b1010111 !
b1010111 +
#1700
b1001111 )
b1001111 -
b1011000 (
b1011000 /
b1010010 '
b1010010 1
b1000110 &
b1000110 3
b1000001 *
b1000001 ,
b1000001 .
b1000001 0
b1000001 2
b1000001 "
b1000001 $
b0 #
b0 %
#1710
b1001111 !
b1001111 +
#1800
b1010010 &
b1010010 3
b1000011 '
b1000011 1
b1000110 (
b1000110 /
b1010101 )
b1010101 -
b1001000 *
b1001000 ,
b1001000 .
b1001000 0
b1001000 2
b1001000 "
b1001000 $
b11 #
b11 %
#1810
b1010010 !
b1010010 +
#1900
b1010111 )
b1010111 -
b1000011 (
b1000011 /
b1001100 '
b1001100 1
b1010011 &
b1010011 3
b1000100 *
b1000100 ,
b1000100 .
b1000100 0
b1000100 2
b1000100 "
b1000100 $
b10 #
b10 %
#1910
b1001100 !
b1001100 +
#2000
b1001101 &
b1001101 3
b1001000 '
b1001000 1
b1000100 (
b1000100 /
b1011010 )
b1011010 -
b1000011 *
b1000011 ,
b1000011 .
b1000011 0
b1000011 2
b1000011 "
b1000011 $
b1 #
b1 %
#2010
b1000100 !
b1000100 +
