Verilog/Behavioral/MEMB.v
`timescale 1ns/100ps

module MEM (output reg [8:1] out, input [8:1] in, input [1:0] setting);

    // Variables for outputs from each black box module
    wire [8:1] out1;
    wire [8:1] out2;
    wire [8:1] out3;
    wire [8:1] out4;

    reg [8:1] inp;

    // 4 black box module threads instantiated
    block1 box1 (out1, inp);
    block2 box2 (out2, inp);
    block3 box3 (out3, inp);
    block4 box4 (out4, inp);
    
    // main thread for selection logic
    always @ (in) begin
        
        inp = in;
        #1;
        case (setting)
            2'b00: begin out <= out1; end
            2'b01: begin out <= out2; end
            2'b10: begin out <= out3; end
            2'b11: begin out <= out4; end
        endcase
    end

endmodule

// Module depicting black box 1 functionality in circuit
module block1 (output reg [8:1] out, input [8:1] in);

    // this thread denotes the behavior of the black box by specifing the mapping choosen for this black box
    always @ (in) begin
        case (in)
            "A": begin out <= "O"; end
            "B": begin out <= "X"; end
            "C": begin out <= "Z"; end
            "D": begin out <= "W"; end
            "E": begin out <= "T"; end
            "F": begin out <= "J"; end
            "G": begin out <= "S"; end
            "H": begin out <= "U"; end
            "I": begin out <= "N"; end
            "J": begin out <= "F"; end
            "K": begin out <= "V"; end
            "L": begin out <= "Y"; end
            "M": begin out <= "R"; end
            "N": begin out <= "I"; end
            "O": begin out <= "A"; end
            "P": begin out <= "Q"; end
            "Q": begin out <= "P"; end
            "R": begin out <= "M"; end
            "S": begin out <= "G"; end
            "T": begin out <= "E"; end
            "U": begin out <= "H"; end
            "V": begin out <= "K"; end
            "W": begin out <= "D"; end
            "X": begin out <= "F"; end
            "Y": begin out <= "L"; end
            "Z": begin out <= "C"; end
        endcase
    end

endmodule

// Module depicting black box 2 functionality in circuit
module block2 (output reg [8:1] out, input [8:1] in);

    // this thread denotes the behavior of the black box by specifing the mapping choosen for this black box
    always @ (in) begin
        case (in)
            "A": begin out <= "X"; end
            "B": begin out <= "V"; end
            "C": begin out <= "D"; end
            "D": begin out <= "C"; end
            "E": begin out <= "S"; end
            "F": begin out <= "H"; end
            "G": begin out <= "O"; end
            "H": begin out <= "F"; end
            "I": begin out <= "Y"; end
            "J": begin out <= "T"; end
            "K": begin out <= "W"; end
            "L": begin out <= "Q"; end
            "M": begin out <= "R"; end
            "N": begin out <= "P"; end
            "O": begin out <= "G"; end
            "P": begin out <= "H"; end
            "Q": begin out <= "L"; end
            "R": begin out <= "M"; end
            "S": begin out <= "E"; end
            "T": begin out <= "J"; end
            "U": begin out <= "Z"; end
            "V": begin out <= "F"; end
            "W": begin out <= "K"; end
            "X": begin out <= "A"; end
            "Y": begin out <= "I"; end
            "Z": begin out <= "U"; end
        endcase
    end

endmodule

// Module depicting black box 3 functionality in circuit
module block3 (output reg [8:1] out, input [8:1] in);

    // this thread denotes the behavior of the black box by specifing the mapping choosen for this black box
    always @ (in) begin
        case (in)
            "A": begin out <= "R"; end
            "B": begin out <= "V"; end
            "C": begin out <= "H"; end
            "D": begin out <= "L"; end
            "E": begin out <= "J"; end
            "F": begin out <= "T"; end
            "G": begin out <= "O"; end
            "H": begin out <= "C"; end
            "I": begin out <= "Y"; end
            "J": begin out <= "E"; end
            "K": begin out <= "Q"; end
            "L": begin out <= "D"; end
            "M": begin out <= "Z"; end
            "N": begin out <= "U"; end
            "O": begin out <= "G"; end
            "P": begin out <= "W"; end
            "Q": begin out <= "K"; end
            "R": begin out <= "A"; end
            "S": begin out <= "X"; end
            "T": begin out <= "F"; end
            "U": begin out <= "N"; end
            "V": begin out <= "B"; end
            "W": begin out <= "P"; end
            "X": begin out <= "S"; end
            "Y": begin out <= "I"; end
            "Z": begin out <= "M"; end
        endcase
    end

endmodule

// Module depicting black box 4 functionality in circuit
module block4 (output reg [8:1] out, input [8:1] in);

    // this thread denotes the behavior of the black box by specifing the mapping choosen for this black box
    always @ (in) begin
        case (in)
            "A": begin out <= "F"; end
            "B": begin out <= "Y"; end
            "C": begin out <= "M"; end
            "D": begin out <= "S"; end
            "E": begin out <= "J"; end
            "F": begin out <= "A"; end
            "G": begin out <= "N"; end
            "H": begin out <= "R"; end
            "I": begin out <= "V"; end
            "J": begin out <= "E"; end
            "K": begin out <= "T"; end
            "L": begin out <= "Q"; end
            "M": begin out <= "C"; end
            "N": begin out <= "G"; end
            "O": begin out <= "X"; end
            "P": begin out <= "U"; end
            "Q": begin out <= "L"; end
            "R": begin out <= "H"; end
            "S": begin out <= "D"; end
            "T": begin out <= "K"; end
            "U": begin out <= "P"; end
            "V": begin out <= "I"; end
            "W": begin out <= "Z"; end
            "X": begin out <= "O"; end
            "Y": begin out <= "B"; end
            "Z": begin out <= "W"; end
        endcase
    end

endmodule

Verilog/Behavioral/MEM.v
`timescale 1ns/100ps

module t_MEM;

    reg [1:0] setting;
    reg [8:1] in;
    wire [8:1] out;

    
    MEM inst(out, in, setting);

    initial begin

        $dumpfile("MEM.vcd");
        $dumpvars(0, t_MEM);

        
        setting = 2'b10;
        in = "H";
        #10;
        setting = 2'b01;
        in = "E";
        #10;
        setting = 2'b00;
        in = "L";
        #10;
        setting = 2'b11;
        in = "L";
        #10;
        setting = 2'b10;
        in = "O";
        #10;
        setting = 2'b01;
        in = "W";
        #10;
        setting = 2'b00;
        in = "O";
        #10;
        setting = 2'b11;
        in = "R";
        #10;
        setting = 2'b10;
        in = "L";
        #10;
        setting = 2'b01;
        in = "D";
        #10;
        #10;
    end

    initial begin
        #1;
        $monitor("\n\t\tinput: %c output: %c\n", in, out);
    end

endmodule

Verilog/Behavioral/MEM.vcd
$date
	Fri Nov 03 22:08:18 2017
$end
$version
	Icarus Verilog
$end
$timescale
	100ps
$end
$scope module t_MEM $end
$var wire 8 ! out [8:1] $end
$var reg 8 " in [8:1] $end
$var reg 2 # setting [1:0] $end
$scope module inst $end
$var wire 8 $ in [8:1] $end
$var wire 2 % setting [1:0] $end
$var wire 8 & out4 [8:1] $end
$var wire 8 ' out3 [8:1] $end
$var wire 8 ( out2 [8:1] $end
$var wire 8 ) out1 [8:1] $end
$var reg 8 * inp [8:1] $end
$var reg 8 + out [8:1] $end
$scope module box1 $end
$var wire 8 , in [8:1] $end
$var reg 8 - out [8:1] $end
$upscope $end
$scope module box2 $end
$var wire 8 . in [8:1] $end
$var reg 8 / out [8:1] $end
$upscope $end
$scope module box3 $end
$var wire 8 0 in [8:1] $end
$var reg 8 1 out [8:1] $end
$upscope $end
$scope module box4 $end
$var wire 8 2 in [8:1] $end
$var reg 8 3 out [8:1] $end
$upscope $end
$upscope $end
$upscope $end
$enddefinitions $end
#0
$dumpvars
b1010010 3
b1001000 2
b1000011 1
b1001000 0
b1000110 /
b1001000 .
b1010101 -
b1001000 ,
bx +
b1001000 *
b1010101 )
b1000110 (
b1000011 '
b1010010 &
b10 %
b1001000 $
b10 #
b1001000 "
bx !
$end
#10
b1000011 !
b1000011 +
#100
b1010100 )
b1010100 -
b1010011 (
b1010011 /
b1001010 '
b1001010 1
b1001010 &
b1001010 3
b1000101 *
b1000101 ,
b1000101 .
b1000101 0
b1000101 2
b1000101 "
b1000101 $
b1 #
b1 %
#110
b1010011 !
b1010011 +
#200
b1010001 &
b1010001 3
b1000100 '
b1000100 1
b1010001 (
b1010001 /
b1011001 )
b1011001 -
b1001100 *
b1001100 ,
b1001100 .
b1001100 0
b1001100 2
b1001100 "
b1001100 $
b0 #
b0 %
#210
b1011001 !
b1011001 +
#300
b11 #
b11 %
#400
b1000001 )
b1000001 -
b1000111 (
b1000111 /
b1000111 '
b1000111 1
b1011000 &
b1011000 3
b1001111 *
b1001111 ,
b1001111 .
b1001111 0
b1001111 2
b1001111 "
b1001111 $
b10 #
b10 %
#410
b1000111 !
b1000111 +
#500
b1011010 &
b1011010 3
b1010000 '
b1010000 1
b1001011 (
b1001011 /
b1000100 )
b1000100 -
b1010111 *
b1010111 ,
b1010111 .
b1010111 0
b1010111 2
b1010111 "
b1010111 $
b1 #
b1 %
#510
b1001011 !
b1001011 +
#600
b1000001 )
b1000001 -
b1000111 (
b1000111 /
b1000111 '
b1000111 1
b1011000 &
b1011000 3
b1001111 *
b1001111 ,
b1001111 .
b1001111 0
b1001111 2
b1001111 "
b1001111 $
b0 #
b0 %
#610
b1000001 !
b1000001 +
#700
b1001000 &
b1001000 3
b1000001 '
b1000001 1
b1001101 (
b1001101 /
b1001101 )
b1001101 -
b1010010 *
b1010010 ,
b1010010 .
b1010010 0
b1010010 2
b1010010 "
b1010010 $
b11 #
b11 %
#710
b1001000 !
b1001000 +
#800
b1011001 )
b1011001 -
b1010001 (
b1010001 /
b1000100 '
b1000100 1
b1010001 &
b1010001 3
b1001100 *
b1001100 ,
b1001100 .
b1001100 0
b1001100 2
b1001100 "
b1001100 $
b10 #
b10 %
#810
b1000100 !
b1000100 +
#900
b1010011 &
b1010011 3
b1001100 '
b1001100 1
b1000011 (
b1000011 /
b1010111 )
b1010111 -
b1000100 *
b1000100 ,
b1000100 .
b1000100 0
b1000100 2
b1000100 "
b1000100 $
b1 #
b1 %
#910
b1000011 !
b1000011 +
