Verilog/Dataflow/MEMD.v
`timescale 1ns/100ps

module MEM (output [8:1] out, input [8:1] in, input [1:0] setting);

    wire [4:0] out1;
    wire [4:0] out2;
    wire [4:0] out3;
    wire [4:0] out4;

    wire [4:0] encodedInput;
    wire [4:0] selectedOut;

    encoder Encoder (encodedInput, in);

    block1 box1 (out1, encodedInput);
    block2 box2 (out2, encodedInput);
    block3 box3 (out3, encodedInput);
    block4 box4 (out4, encodedInput);

    // selection 
    assign selectedOut[0] = (~setting[0] & ~setting[1] & out1[0]) | (setting[0] & ~setting[1] & out2[0]) | (~setting[0] & setting[1] & out3[0]) | (setting[0] & setting[1] & out4[0]);
    assign selectedOut[1] = (~setting[0] & ~setting[1] & out1[1]) | (setting[0] & ~setting[1] & out2[1]) | (~setting[0] & setting[1] & out3[1]) | (setting[0] & setting[1] & out4[1]);
    assign selectedOut[2] = (~setting[0] & ~setting[1] & out1[2]) | (setting[0] & ~setting[1] & out2[2]) | (~setting[0] & setting[1] & out3[2]) | (setting[0] & setting[1] & out4[2]);
    assign selectedOut[3] = (~setting[0] & ~setting[1] & out1[3]) | (setting[0] & ~setting[1] & out2[3]) | (~setting[0] & setting[1] & out3[3]) | (setting[0] & setting[1] & out4[3]);
    assign selectedOut[4] = (~setting[0] & ~setting[1] & out1[4]) | (setting[0] & ~setting[1] & out2[4]) | (~setting[0] & setting[1] & out3[4]) | (setting[0] & setting[1] & out4[4]);
    
    
    decoder Decoder (out, selectedOut);
    

endmodule

module block1 (output [4:0] out, input [4:0] in);

    

endmodule


module block2 (output [4:0] out, input [4:0] in);

   
    

endmodule

module block3 (output [4:0] out, input [4:0] in);

    assign out[0]=(~in[4]&~in[3]&~in[2])|(~in[3]&in[2]&~in[1])|(~in[2]&in[1]&in[0])|(in[2]&~in[1]&~in[0])|(in[4]&in[1]&~in[0]);
    assign out[1]=(in[2]&in[1])|(~in[4]&~in[3]&in[1])|(~in[4]&in[1]&in[0])|(~in[4]&~in[3]&in[2]&in[0])|(in[4]&~in[3]&~in[2]&~in[0]);
    assign out[2]=(~in[3]&in[1]&~in[0])|(in[3]&~in[1]&in[0])|(in[3]&in[2]&in[1])|(in[4]&in[2]&~in[0])|(in[4]&~in[2]&in[1])|(~in[4]&~in[2]&~in[1]&in[0]);
    assign out[3]=(in[4]&in[3])|(~in[3]&in[2]&~in[0])|(in[3]&~in[1]&~in[0])|(in[4]&~in[1]&~in[0])|(~in[4]&~in[3]&~in[2]&in[1]&in[0]);
    assign out[4]=(in[3]&in[2]&~in[1])|(in[3]&in[2]&in[0])|(~in[4]&~in[3]&~in[2]&~in[1])|(~in[4]&~in[3]&~in[1]&in[0])|(~in[4]&in[3]&~in[2]&~in[0])|(in[4]&~in[2]&in[1]&~in[0])|(in[4]&in[2]&in[1]&in[0]);
    

endmodule

module block4 (output [4:0] out, input [4:0] in);

    assign out[0]=(in[4]&~in[0])|(~in[3]&~in[1]&~in[0])|(in[2]&in[1]&~in[0])|(in[3]&~in[2]&~in[0])|(~in[4]&~in[3]&in[2]&in[1])|(in[4]&~in[3]&~in[2]&~in[1]);
    assign out[1]=(in[4]&~in[3]&~in[2])|(in[3]&in[1]&~in[0])|(in[3]&in[2]&~in[1])|(in[4]&~in[2]&in[0])|(in[4]&in[1]&in[0])|(~in[3]&~in[2]&in[1]&in[0])|(in[4]&~in[3]&~in[1]&~in[0]);
    assign out[2]=(in[3]&~in[1]&in[0])|(in[3]&in[2]&in[1])|(~in[4]&~in[2]&~in[1]&~in[0])|(~in[4]&~in[3]&in[1]&~in[0])|(in[4]&~in[2]&~in[1]&in[0])|(in[4]&in[2]&~in[1]&~in[0])|(in[4]&in[2]&in[1]&in[0]);
    assign out[3]=(in[4]&in[2])|(~in[3]&in[2]&~in[0])|(in[4]&in[1]&in[0])|(~in[4]&~in[3]&in[1]&~in[0])|(in[4]&~in[3]&~in[1]&~in[0])|(~in[4]&~in[3]&~in[2]&~in[1]&in[0]);
    assign out[4]=(in[3]&in[1])|(~in[4]&in[1]&in[0])|(in[4]&in[3]&in[0])|(~in[4]&~in[3]&~in[2]&in[0])|(~in[4]&in[3]&~in[2]&~in[0])|(in[4]&in[2]&in[1]&~in[0]);

endmodule

module encoder (output [4:0] encodedInput, input [8:1] in);

    wire [8:1] res;

    assign res = in - "A";

    assign encodedInput[4] = res[5];
    assign encodedInput[3] = res[4];
    assign encodedInput[2] = res[3];
    assign encodedInput[1] = res[2];
    assign encodedInput[0] = res[1];

endmodule

module decoder (output [8:1] out, input [4:0] selectedOut);

    wire [8:1] res;

    assign res[8] = 1'b0;
    assign res[7] = 1'b0;
    assign res[6] = 1'b0;
    assign res[5] = selectedOut[4];
    assign res[4] = selectedOut[3];
    assign res[3] = selectedOut[2];
    assign res[2] = selectedOut[1];
    assign res[1] = selectedOut[0];

    assign out = res + "A";

endmodule

Verilog/Dataflow/MEM.v
`timescale 1ns/100ps

module t_MEM;

    reg [1:0] setting;
    reg [8:1] in;
    wire [8:1] out;

    
    MEM inst(out, in, setting);

    initial begin

        $dumpfile("MEM.vcd");
        $dumpvars(0, t_MEM);

        in = "H";
        setting = 2'b11;
        #10;
        in = "E";
        setting = 2'b10;
        #10;
        in = "L";
        setting = 2'b10;
        #10;
        in = "L";
        setting = 2'b11;
        #10;
        in = "O";
        setting = 2'b10;
        #10;
        in = "W";
        setting = 2'b10;
        #10;
        in = "O";
        setting = 2'b11;
        #10;
        in = "R";
        setting = 2'b10;
        #10;
        in = "L";
        setting = 2'b10;
        #10;
        in = "D";
        setting = 2'b10;
        #10;
        #10;
    end

    initial begin
        #1;
        $monitor("\n\t\tinput: %c output: %c\n", in, out);
    end

endmodule

Verilog/Dataflow/MEM.vcd
$date
	Fri Nov  3 00:25:48 2017
$end
$version
	Icarus Verilog
$end
$timescale
	100ps
$end
$scope module t_MEM $end
$var wire 8 ! out [8:1] $end
$var reg 8 " in [8:1] $end
$var reg 2 # setting [1:0] $end
$scope module inst $end
$var wire 5 $ encodedInput [4:0] $end
$var wire 8 % in [8:1] $end
$var wire 8 & out [8:1] $end
$var wire 5 ' out1 [4:0] $end
$var wire 5 ( out2 [4:0] $end
$var wire 5 ) out3 [4:0] $end
$var wire 5 * out4 [4:0] $end
$var wire 5 + selectedOut [4:0] $end
$var wire 2 , setting [1:0] $end
$scope module Encoder $end
$var wire 5 - encodedInput [4:0] $end
$var wire 8 . in [8:1] $end
$var wire 8 / res [8:1] $end
$upscope $end
$scope module box1 $end
$var wire 5 0 in [4:0] $end
$var wire 5 1 out [4:0] $end
$upscope $end
$scope module box2 $end
$var wire 5 2 in [4:0] $end
$var wire 5 3 out [4:0] $end
$upscope $end
$scope module box3 $end
$var wire 5 4 in [4:0] $end
$var wire 5 5 out [4:0] $end
$upscope $end
$scope module box4 $end
$var wire 5 6 in [4:0] $end
$var wire 5 7 out [4:0] $end
$upscope $end
$scope module Decoder $end
$var wire 8 8 out [8:1] $end
$var wire 8 9 res [8:1] $end
$var wire 5 : selectedOut [4:0] $end
$upscope $end
$upscope $end
$upscope $end
$enddefinitions $end
#0
$dumpvars
b10001 :
b10001 9
b1010010 8
b10001 7
b111 6
b10 5
b111 4
bz 3
b111 2
bz 1
b111 0
b111 /
b1001000 .
b111 -
b11 ,
b10001 +
b10001 *
b10 )
bz (
bz '
b1010010 &
b1001000 %
b111 $
b11 #
b1001000 "
b1010010 !
$end
#100
b1001 )
b1001 5
b1001 9
b1001010 !
b1001010 &
b1001010 8
b1001 *
b1001 7
b1001 +
b1001 :
b100 $
b100 -
b100 0
b100 2
b100 4
b100 6
b10 #
b10 ,
b1000101 "
b1000101 %
b1000101 .
b100 /
#200
b11 9
b1000100 !
b1000100 &
b1000100 8
b11 +
b11 :
b10000 *
b10000 7
b11 )
b11 5
b1011 $
b1011 -
b1011 0
b1011 2
b1011 4
b1011 6
b1001100 "
b1001100 %
b1001100 .
b1011 /
#300
b10000 9
b1010001 !
b1010001 &
b1010001 8
b10000 +
b10000 :
b11 #
b11 ,
#400
b10111 *
b10111 7
b110 )
b110 5
b110 9
b1000111 !
b1000111 &
b1000111 8
b110 +
b110 :
b1110 $
b1110 -
b1110 0
b1110 2
b1110 4
b1110 6
b10 #
b10 ,
b1001111 "
b1001111 %
b1001111 .
b1110 /
#500
b1111 9
b1010000 !
b1010000 &
b1010000 8
b1111 +
b1111 :
b11001 *
b11001 7
b1111 )
b1111 5
b10110 $
b10110 -
b10110 0
b10110 2
b10110 4
b10110 6
b1010111 "
b1010111 %
b1010111 .
b10110 /
#600
b10111 *
b10111 7
b10111 9
b1011000 !
b1011000 &
b1011000 8
b110 )
b110 5
b10111 +
b10111 :
b1110 $
b1110 -
b1110 0
b1110 2
b1110 4
b1110 6
b11 #
b11 ,
b1001111 "
b1001111 %
b1001111 .
b1110 /
#700
b111 *
b111 7
b0 )
b0 5
b0 9
b1000001 !
b1000001 &
b1000001 8
b0 +
b0 :
b10001 $
b10001 -
b10001 0
b10001 2
b10001 4
b10001 6
b10 #
b10 ,
b1010010 "
b1010010 %
b1010010 .
b10001 /
#800
b11 9
b1000100 !
b1000100 &
b1000100 8
b11 +
b11 :
b11 )
b11 5
b10000 *
b10000 7
b1011 $
b1011 -
b1011 0
b1011 2
b1011 4
b1011 6
b1001100 "
b1001100 %
b1001100 .
b1011 /
#900
b1011 9
b1001100 !
b1001100 &
b1001100 8
b1011 +
b1011 :
b1011 )
b1011 5
b10010 *
b10010 7
b11 $
b11 -
b11 0
b11 2
b11 4
b11 6
b1000100 "
b1000100 %
b1000100 .
b11 /
