Verilog/Dataflow/MEMD.v
`timescale 1ns/100ps

module MEM (output [8:1] out, input [8:1] in, input [1:0] setting);

    wire [4:0] out1;
    wire [4:0] out2;
    wire [4:0] out3;
    wire [4:0] out4;

    wire [4:0] encodedInput;
    wire [4:0] selectedOut;

    encoder Encoder (encodedInput, in);

    //block1 box1 (out1, encodedInput);
    //block2 box2 (out2, encodedInput);
    //block3 box3 (out3, encodedInput);
    //block4 box4 (out4, encodedInput);

    assign out1 = 5'b00010;

    // selection 
    assign selectedOut[0] = (~setting[0] & ~setting[1] & out1[0]) | (~setting[0] & setting[1] & out2[0]) | (setting[0] & ~setting[1] & out3[0]) | (setting[0] & setting[1] & out4[0]);
    assign selectedOut[1] = (~setting[0] & ~setting[1] & out1[1]) | (~setting[0] & setting[1] & out2[1]) | (setting[0] & ~setting[1] & out3[1]) | (setting[0] & setting[1] & out4[1]);
    assign selectedOut[2] = (~setting[0] & ~setting[1] & out1[2]) | (~setting[0] & setting[1] & out2[2]) | (setting[0] & ~setting[1] & out3[2]) | (setting[0] & setting[1] & out4[2]);
    assign selectedOut[3] = (~setting[0] & ~setting[1] & out1[3]) | (~setting[0] & setting[1] & out2[3]) | (setting[0] & ~setting[1] & out3[3]) | (setting[0] & setting[1] & out4[3]);
    assign selectedOut[4] = (~setting[0] & ~setting[1] & out1[4]) | (~setting[0] & setting[1] & out2[4]) | (setting[0] & ~setting[1] & out3[4]) | (setting[0] & setting[1] & out4[4]);
    
    
    decoder Decoder (out, selectedOut);
    

endmodule

module block1 (output [4:0] out, input [4:0] in);

    

endmodule


module block2 (output [4:0] out, input [4:0] in);

   
    

endmodule

module block3 (output [4:0] out, input [4:0] in);

    

endmodule

module block4 (output [4:0] out, input [4:0] in);

   

endmodule

module encoder (output [4:0] encodedInput, input [8:1] in);

    wire [8:1] res;

    assign res = in - "A";

    assign encodedInput[4] = res[5];
    assign encodedInput[3] = res[4];
    assign encodedInput[2] = res[3];
    assign encodedInput[1] = res[2];
    assign encodedInput[0] = res[1];

endmodule

module decoder (output [8:1] out, input [4:0] selectedOut);

    wire [8:1] res;

    assign res[8] = 1'b0;
    assign res[7] = 1'b0;
    assign res[6] = 1'b0;
    assign res[5] = selectedOut[4];
    assign res[4] = selectedOut[3];
    assign res[3] = selectedOut[2];
    assign res[2] = selectedOut[1];
    assign res[1] = selectedOut[0];

    assign out = res + "A";

endmodule

Verilog/Dataflow/MEM.v
`timescale 1ns/100ps

module t_MEM;

    reg [1:0] setting;
    reg [8:1] in;
    wire [8:1] out;

    
    MEM inst(out, in, setting);

    initial begin

        $dumpfile("MEM.vcd");
        $dumpvars(0, t_MEM);

        in = "H";
        setting = 2'b10;
        #10;
        in = "E";
        setting = 2'b01;
        #10;
        in = "L";
        setting = 2'b00;
        #10;
        in = "L";
        setting = 2'b11;
        #10;
        in = "O";
        setting = 2'b10;
        #10;
        in = "W";
        setting = 2'b01;
        #10;
        in = "O";
        setting = 2'b00;
        #10;
        in = "R";
        setting = 2'b11;
        #10;
        in = "L";
        setting = 2'b10;
        #10;
        in = "D";
        setting = 2'b01;
        #10;
        #10;
    end

    initial begin
        #1;
        $monitor("\n\t\tinput: %c output: %c\n", in, out);
    end

endmodule

Verilog/Dataflow/MEM.vcd
$date
	Thu Nov 02 22:21:02 2017
$end
$version
	Icarus Verilog
$end
$timescale
	100ps
$end
$scope module t_MEM $end
$var wire 8 ! out [8:1] $end
$var reg 8 " in [8:1] $end
$var reg 2 # setting [1:0] $end
$scope module inst $end
$var wire 8 $ in [8:1] $end
$var wire 5 % out1 [4:0] $end
$var wire 5 & out2 [4:0] $end
$var wire 5 ' out3 [4:0] $end
$var wire 5 ( out4 [4:0] $end
$var wire 2 ) setting [1:0] $end
$var wire 5 * selectedOut [4:0] $end
$var wire 8 + out [8:1] $end
$var wire 5 , encodedInput [4:0] $end
$scope module Decoder $end
$var wire 5 - selectedOut [4:0] $end
$var wire 8 . res [8:1] $end
$var wire 8 / out [8:1] $end
$upscope $end
$scope module Encoder $end
$var wire 8 0 in [8:1] $end
$var wire 8 1 res [8:1] $end
$var wire 5 2 encodedInput [4:0] $end
$upscope $end
$upscope $end
$upscope $end
$enddefinitions $end
#0
$dumpvars
b111 2
b111 1
b1001000 0
bx /
b0xxxxx .
bx -
b111 ,
bx +
bx *
b10 )
bz (
bz '
bz &
b10 %
b1001000 $
b10 #
b1001000 "
bx !
$end
#100
b100 ,
b100 2
b1 #
b1 )
b100 1
b1000101 "
b1000101 $
b1000101 0
#200
b1000011 !
b1000011 +
b1000011 /
b10 .
b10 *
b10 -
b1011 ,
b1011 2
b0 #
b0 )
b1011 1
b1001100 "
b1001100 $
b1001100 0
#300
bx !
bx +
bx /
b0xxxxx .
bx *
bx -
b11 #
b11 )
#400
bx !
bx +
bx /
b0xxxxx .
bx *
bx -
b1110 ,
b1110 2
b10 #
b10 )
b1110 1
b1001111 "
b1001111 $
b1001111 0
#500
b10110 ,
b10110 2
b1 #
b1 )
b10110 1
b1010111 "
b1010111 $
b1010111 0
#600
b1000011 !
b1000011 +
b1000011 /
b10 .
b10 *
b10 -
b1110 ,
b1110 2
b0 #
b0 )
b1110 1
b1001111 "
b1001111 $
b1001111 0
#700
bx !
bx +
bx /
b0xxxxx .
bx *
bx -
b10001 ,
b10001 2
b11 #
b11 )
b10001 1
b1010010 "
b1010010 $
b1010010 0
#800
bx !
bx +
bx /
b0xxxxx .
bx *
bx -
b1011 ,
b1011 2
b10 #
b10 )
b1011 1
b1001100 "
b1001100 $
b1001100 0
#900
b11 ,
b11 2
b1 #
b1 )
b11 1
b1000100 "
b1000100 $
b1000100 0
