Verilog/Dataflow/MEMD.v
`timescale 1ns/100ps

// 
module MEM (output [8:1] out, input [8:1] in, input [1:0] setting);

    // Variables for outputs from each black box module
    wire [4:0] out1;
    wire [4:0] out2;
    wire [4:0] out3;
    wire [4:0] out4;

    // Varible to get 5 bit binary encoding for the 8 bit ASCII character
    wire [4:0] encodedInput;

    // Variable to select the bits from all black boxes based on setting
    wire [4:0] selectedOut;

    // Encoder module thread instantiated
    encoder Encoder (encodedInput, in);

    block1 box1 (out1, encodedInput);
    block2 box2 (out2, encodedInput);
    block3 box3 (out3, encodedInput);
    block4 box4 (out4, encodedInput);

    // Selection logic
    assign selectedOut[0] = (~setting[0] & ~setting[1] & out1[0]) | (setting[0] & ~setting[1] & out2[0]) | (~setting[0] & setting[1] & out3[0]) | (setting[0] & setting[1] & out4[0]);
    assign selectedOut[1] = (~setting[0] & ~setting[1] & out1[1]) | (setting[0] & ~setting[1] & out2[1]) | (~setting[0] & setting[1] & out3[1]) | (setting[0] & setting[1] & out4[1]);
    assign selectedOut[2] = (~setting[0] & ~setting[1] & out1[2]) | (setting[0] & ~setting[1] & out2[2]) | (~setting[0] & setting[1] & out3[2]) | (setting[0] & setting[1] & out4[2]);
    assign selectedOut[3] = (~setting[0] & ~setting[1] & out1[3]) | (setting[0] & ~setting[1] & out2[3]) | (~setting[0] & setting[1] & out3[3]) | (setting[0] & setting[1] & out4[3]);
    assign selectedOut[4] = (~setting[0] & ~setting[1] & out1[4]) | (setting[0] & ~setting[1] & out2[4]) | (~setting[0] & setting[1] & out3[4]) | (setting[0] & setting[1] & out4[4]);
    
    // Decoder module thread instantiated
    decoder Decoder (out, selectedOut);
    

endmodule

// Module depicting black box 1 functionality in circuit
module block1 (output [4:0] out, input [4:0] in);

    // F5 = D'CE' + AD'E' + ACD + A'C'DE' + A'B'C'D' + A'B'D'E 
    assign out[0] = (~in[1] & in[2] & ~in[0]) | (in[4] & ~in[1] & ~in[0]) | (in[4] & in[2] & in[1]) | (~in[4] & ~in[2] & in[1] & ~in[0]) | (~in[4] & in[3] & ~in[2] & ~in[1]) | (~in[4] & ~in[3] & ~in[1] & in[0]);
    
    // F4 = AE' + AB + B'D'E' + B'CE' + ACD' + A'B'C'E 
    assign out[1] = (in[4] & ~in[0]) | (in[4] & in[3]) | (~in[3] & ~in[1] & ~in[0]) | (~in[3] & in[2] & ~in[0]) | (in[4] & in[2] & ~in[1]) | (~in[4] & ~in[3] & ~in[2] & in[0]);
    
    // F3 = A'C'D' + AB'C' + A'B'DE + A'BC'E' + AB'D'E'
    assign out[2] = (~in[4] & ~in[2] & ~in[1]) | (in[4] & ~in[3] & ~in[2]) | (~in[4] & ~in[3] & in[1] & in[0]) | (~in[4] & in[3] & ~in[2] & ~in[0]) | (in[4] & ~in[3] & ~in[1] & ~in[0]);
    
    // F2 = C'D'E' + CD'E + A'B'C'E' + AB'C'D' + BC'DE;
    assign out[3] = (~in[2] & ~in[1] & ~in[0]) | (in[2] & ~in[1] & in[0]) | (~in[4] & ~in[3] & ~in[2] & ~in[0]) | (in[4] & ~in[3] & ~in[2] & ~in[1]) | (in[3] & ~in[2] & in[1] & in[0]);
    
    // F1 = A'B'D + A'C'D + A'DE + A'B'C'E + A'CD'E'
    assign out[4] = (~in[4] & ~in[3] & in[1]) | (~in[4] & ~in[2] & in[1]) | (~in[4] & in[1] & in[0]) | (~in[4] & ~in[3] & ~in[2] & in[0]) | (~in[4] & in[2] & ~in[1] & ~in[0]);

endmodule

// Module depicting black box 2 functionality in circuit
module block2 (output [4:0] out, input [4:0] in);

    // F5 = A'D'E + A'CE + BCD' + ACD' + A'B'C'E' + B'C'D'E' + AC'DE 
    assign out[0] = (~in[4] & ~in[2] & in[0]) | (~in[4] & in[2] & in[0]) | (in[3] & in[2] & ~in[1]) | (in[4] & in[2] & ~in[1]) | (~in[4] & ~in[3] & ~in[2] & ~in[0]) | (~in[3] & ~in[2] & ~in[1] & ~in[0]) | (in[4] & ~in[2] & in[1] & in[0]);
    
    // F4 = A'DE' + CDE' + B'C'D'E' + A'B'C'D + A'B'CD' + A'BD'E
    assign out[1] = (~in[4] & in[1] & ~in[0]) | (in[2] & in[1] & ~in[0]) | (~in[3] & ~in[2] & ~in[1] & ~in[0]) | (~in[4] & ~in[3] & ~in[2] & in[1]) | (~in[4] & ~in[3] & in[2] & ~in[1]) | (~in[4] & in[3] & ~in[1] & in[0]);
    
    // F3 = A'CE + A'CD + BDE' + AC'D'E + A'B'C'D' + AC'DE'
    assign out[2] = (~in[4] & in[2] & in[0]) | (~in[4] & in[2] & in[1]) | (in[3] & in[1] & ~in[0]) | (in[4] & ~in[2] & ~in[1] & in[0]) | (~in[4] & ~in[3] & ~in[2] & ~in[1]) | (in[4] & ~in[2] & in[1] & ~in[0]);
    
    // F2 = BCE + AD'E' + B'CDE' + BC'D'E' + AB'C'E
    assign out[3] = (in[3] & in[2] & in[0]) | (in[4] & ~in[1] & ~in[0]) | (~in[3] & in[2] & in[1] & ~in[0]) | (in[3] & ~in[2] & ~in[1] & ~in[0]) | (in[4] & ~in[3] & ~in[2] & in[0]);
    
    // F1 = A'C'D' + A'BC' + CD'E' + BC'E
    assign out[4] = (~in[4] & ~in[2] & ~in[1]) | (~in[4] & in[3] & ~in[2]) | (in[2] & ~in[1] & ~in[0]) | (in[3] & ~in[2] & in[0]);

endmodule

// Module depicting black box 3 functionality in circuit
module block3 (output [4:0] out, input [4:0] in);

    // 
    assign out[0] = (~in[4]&~in[3]&~in[2])|(~in[3]&in[2]&~in[1])|(~in[2]&in[1]&in[0])|(in[2]&~in[1]&~in[0])|(in[4]&in[1]&~in[0]);
    // 
    assign out[1] = (in[2]&in[1])|(~in[4]&~in[3]&in[1])|(~in[4]&in[1]&in[0])|(~in[4]&~in[3]&in[2]&in[0])|(in[4]&~in[3]&~in[2]&~in[0]);
    // 
    assign out[2] = (~in[3]&in[1]&~in[0])|(in[3]&~in[1]&in[0])|(in[3]&in[2]&in[1])|(in[4]&in[2]&~in[0])|(in[4]&~in[2]&in[1])|(~in[4]&~in[2]&~in[1]&in[0]);
    // 
    assign out[3] = (in[4]&in[3])|(~in[3]&in[2]&~in[0])|(in[3]&~in[1]&~in[0])|(in[4]&~in[1]&~in[0])|(~in[4]&~in[3]&~in[2]&in[1]&in[0]);
    // 
    assign out[4] = (in[3]&in[2]&~in[1])|(in[3]&in[2]&in[0])|(~in[4]&~in[3]&~in[2]&~in[1])|(~in[4]&~in[3]&~in[1]&in[0])|(~in[4]&in[3]&~in[2]&~in[0])|(in[4]&~in[2]&in[1]&~in[0])|(in[4]&in[2]&in[1]&in[0]);
    

endmodule

// Module depicting black box 4 functionality in circuit
module block4 (output [4:0] out, input [4:0] in);

    //
    assign out[0] = (in[4]&~in[0])|(~in[3]&~in[1]&~in[0])|(in[2]&in[1]&~in[0])|(in[3]&~in[2]&~in[0])|(~in[4]&~in[3]&in[2]&in[1])|(in[4]&~in[3]&~in[2]&~in[1]);
    //
    assign out[1] = (in[4]&~in[3]&~in[2])|(in[3]&in[1]&~in[0])|(in[3]&in[2]&~in[1])|(in[4]&~in[2]&in[0])|(in[4]&in[1]&in[0])|(~in[3]&~in[2]&in[1]&in[0])|(in[4]&~in[3]&~in[1]&~in[0]);
    //
    assign out[2] = (in[3]&~in[1]&in[0])|(in[3]&in[2]&in[1])|(~in[4]&~in[2]&~in[1]&~in[0])|(~in[4]&~in[3]&in[1]&~in[0])|(in[4]&~in[2]&~in[1]&in[0])|(in[4]&in[2]&~in[1]&~in[0])|(in[4]&in[2]&in[1]&in[0]);
    //
    assign out[3] = (in[4]&in[2])|(~in[3]&in[2]&~in[0])|(in[4]&in[1]&in[0])|(~in[4]&~in[3]&in[1]&~in[0])|(in[4]&~in[3]&~in[1]&~in[0])|(~in[4]&~in[3]&~in[2]&~in[1]&in[0]);
    //
    assign out[4] = (in[3]&in[1])|(~in[4]&in[1]&in[0])|(in[4]&in[3]&in[0])|(~in[4]&~in[3]&~in[2]&in[0])|(~in[4]&in[3]&~in[2]&~in[0])|(in[4]&in[2]&in[1]&~in[0]);

endmodule

module encoder (output [4:0] encodedInput, input [8:1] in);

    wire [8:1] res;

    assign res = in - "A";

    assign encodedInput[4] = res[5];
    assign encodedInput[3] = res[4];
    assign encodedInput[2] = res[3];
    assign encodedInput[1] = res[2];
    assign encodedInput[0] = res[1];

endmodule

module decoder (output [8:1] out, input [4:0] selectedOut);

    wire [8:1] res;

    assign res[8] = 1'b0;
    assign res[7] = 1'b0;
    assign res[6] = 1'b0;
    assign res[5] = selectedOut[4];
    assign res[4] = selectedOut[3];
    assign res[3] = selectedOut[2];
    assign res[2] = selectedOut[1];
    assign res[1] = selectedOut[0];

    assign out = res + "A";

endmodule

Verilog/Dataflow/MEM.v
`timescale 1ns/100ps

/*
        TITLE: THE MODIFIED ENIGMA MACHINE

        REG NO: 16CO154-16CO233

        ABSTRACT: A circuit that encrypts data by mapping each alphabet to another alphabet randomly. 
                  This will be done in such a way that if the same alphabet is repeated, 
                  the encrypted alphabet will not be the same always.

        FUNCTIONALITIES: The following modules are present

                            a) Encoder: It is an alphabet to binary encoder
                            b) Decoder: It is a binary to alphabet decoder
                            
                            There is an input array- setting, which helps in deciding which block must encode/decode data
                            
                            c) Block 1,2,3 and 4: Blocks which encode/decode data using boolean equations

        BRIEF DESCRIPTION OF CODE:  The user enters some data (given in test-bench) and sets a code to encrypt the data.
                                    This data is then encrypted in the following module and then displayed.
                                    For decrypting the same data must be entered with same settings.
                                    For making the process easier there is an alphabet-binary encoder along with a binary-alphabet decoder.
*/

module t_MEM;

    reg [1:0] setting;
    reg [8:1] in;
    wire [8:1] out;

    
    MEM inst(out, in, setting);

    initial begin

        $dumpfile("MEM.vcd");
        $dumpvars(0, t_MEM);

        $display("\n\n ================== THE MODIFIED ENIGMA MACHINE ==================\n");
        $display("\n\t------ ENCRYPTING: \"HELLOWORLD\", SETTINGS: 2103 ------\n");

        setting = 2'b10;
        in = "H";
        #10;
        setting = 2'b01;
        in = "E";
        #10;
        setting = 2'b00;
        in = "L";
        #10;
        setting = 2'b11;
        in = "L";
        #10;
        setting = 2'b10;
        in = "O";
        #10;
        setting = 2'b01;
        in = "W";
        #10;
        setting = 2'b00;
        in = "O";
        #10;
        setting = 2'b11;
        in = "R";
        #10;
        setting = 2'b10;
        in = "L";
        #10;
        setting = 2'b01;
        in = "D";
        #10;

        $display("\n\t------ DECRYPTING: \"CSYQGKAHDC\", SETTINGS: 2103 ------\n");

        #10;
        setting = 2'b10;
        in = "C";
        #10;
        setting = 2'b01;
        in = "S";
        #10;
        setting = 2'b00;
        in = "Y";
        #10;
        setting = 2'b11;
        in = "Q";
        #10;
        setting = 2'b10;
        in = "G";
        #10;
        setting = 2'b01;
        in = "K";
        #10;
        setting = 2'b00;
        in = "A";
        #10;
        setting = 2'b11;
        in = "H";
        #10;
        setting = 2'b10;
        in = "D";
        #10;
        setting = 2'b01;
        in = "C";
        #10;
    end


    initial begin
        #1;
        $monitor("\n\t\tinput: %c output: %c\n", in, out);
    end

endmodule

Verilog/Dataflow/MEM.vcd
$date
	Fri Nov 03 22:05:53 2017
$end
$version
	Icarus Verilog
$end
$timescale
	100ps
$end
$scope module t_MEM $end
$var wire 8 ! out [8:1] $end
$var reg 8 " in [8:1] $end
$var reg 2 # setting [1:0] $end
$scope module inst $end
$var wire 8 $ in [8:1] $end
$var wire 2 % setting [1:0] $end
$var wire 5 & selectedOut [4:0] $end
$var wire 5 ' out4 [4:0] $end
$var wire 5 ( out3 [4:0] $end
$var wire 5 ) out2 [4:0] $end
$var wire 5 * out1 [4:0] $end
$var wire 8 + out [8:1] $end
$var wire 5 , encodedInput [4:0] $end
$scope module Decoder $end
$var wire 5 - selectedOut [4:0] $end
$var wire 8 . res [8:1] $end
$var wire 8 / out [8:1] $end
$upscope $end
$scope module Encoder $end
$var wire 8 0 in [8:1] $end
$var wire 8 1 res [8:1] $end
$var wire 5 2 encodedInput [4:0] $end
$upscope $end
$scope module box1 $end
$var wire 5 3 in [4:0] $end
$var wire 5 4 out [4:0] $end
$upscope $end
$scope module box2 $end
$var wire 5 5 in [4:0] $end
$var wire 5 6 out [4:0] $end
$upscope $end
$scope module box3 $end
$var wire 5 7 in [4:0] $end
$var wire 5 8 out [4:0] $end
$upscope $end
$scope module box4 $end
$var wire 5 9 in [4:0] $end
$var wire 5 : out [4:0] $end
$upscope $end
$upscope $end
$upscope $end
$enddefinitions $end
#0
$dumpvars
b10001 :
b111 9
b10 8
b111 7
b101 6
b111 5
b10100 4
b111 3
b111 2
b111 1
b1001000 0
b1000011 /
b10 .
b10 -
b111 ,
b1000011 +
b10100 *
b101 )
b10 (
b10001 '
b10 &
b10 %
b1001000 $
b10 #
b1001000 "
b1000011 !
$end
#100
b1001 (
b1001 8
b10010 )
b10010 6
b10011 *
b10011 4
b1010011 !
b1010011 +
b1010011 /
b10010 .
b1001 '
b1001 :
b10010 &
b10010 -
b100 ,
b100 2
b100 3
b100 5
b100 7
b100 9
b100 1
b1000101 "
b1000101 $
b1000101 0
b1 #
b1 %
#200
b10000 '
b10000 :
b1011001 !
b1011001 +
b1011001 /
b11000 .
b10001 )
b10001 6
b11000 &
b11000 -
b11000 *
b11000 4
b11 (
b11 8
b1011 ,
b1011 2
b1011 3
b1011 5
b1011 7
b1011 9
b1011 1
b1001100 "
b1001100 $
b1001100 0
b0 #
b0 %
#300
b1010001 !
b1010001 +
b1010001 /
b10000 .
b10000 &
b10000 -
b11 #
b11 %
#400
b110 )
b110 6
b10111 '
b10111 :
b110 (
b110 8
b1000111 !
b1000111 +
b1000111 /
b110 .
b0 *
b0 4
b110 &
b110 -
b1110 ,
b1110 2
b1110 3
b1110 5
b1110 7
b1110 9
b1110 1
b1001111 "
b1001111 $
b1001111 0
b10 #
b10 %
#500
b1010 )
b1010 6
b11001 '
b11001 :
b11 *
b11 4
b1001011 !
b1001011 +
b1001011 /
b1010 .
b1111 (
b1111 8
b1010 &
b1010 -
b10110 ,
b10110 2
b10110 3
b10110 5
b10110 7
b10110 9
b10110 1
b1010111 "
b1010111 $
b1010111 0
b1 #
b1 %
#600
b0 *
b0 4
b110 )
b110 6
b1000001 !
b1000001 +
b1000001 /
b0 .
b10111 '
b10111 :
b0 &
b0 -
b110 (
b110 8
b1110 ,
b1110 2
b1110 3
b1110 5
b1110 7
b1110 9
b1110 1
b1001111 "
b1001111 $
b1001111 0
b0 #
b0 %
#700
b111 '
b111 :
b0 (
b0 8
b1100 )
b1100 6
b1100 *
b1100 4
b1001000 !
b1001000 +
b1001000 /
b111 .
b111 &
b111 -
b10001 ,
b10001 2
b10001 3
b10001 5
b10001 7
b10001 9
b10001 1
b1010010 "
b1010010 $
b1010010 0
b11 #
b11 %
#800
b11000 *
b11000 4
b10001 )
b10001 6
b11 (
b11 8
b10000 '
b10000 :
b1000100 !
b1000100 +
b1000100 /
b11 .
b11 &
b11 -
b1011 ,
b1011 2
b1011 3
b1011 5
b1011 7
b1011 9
b1011 1
b1001100 "
b1001100 $
b1001100 0
b10 #
b10 %
#900
b1011 (
b1011 8
b10010 '
b10010 :
b11 )
b11 6
b10110 *
b10110 4
b1000100 !
b1000100 +
b1000100 /
b11 .
b11 &
b11 -
b11 ,
b11 2
b11 3
b11 5
b11 7
b11 9
b11 1
b1000100 "
b1000100 $
b1000100 0
b1 #
b1 %
