Verilog-154-233/Behavioral/VerilogBM-154-233.v
`timescale 1ns/100ps

/*
        TITLE: THE MODIFIED ENIGMA MACHINE

        REG NO: 16CO154-16CO233

        ABSTRACT: A circuit that encrypts data by mapping each alphabet to another alphabet randomly.
                  Thus a message is encrypted by a user based on a setting decided by the user and the receiver.
                  The receiver has to enter the encrypted data along with the same decided setting to get the desired (decrypted) message.

        FUNCTIONALITIES: The following modules are present:

                            1) VerilogBM_154_233: Handles the selection of black box modules as per the setting along with passing inputs and outputs
                            2) block1, block2, block3, block4 : These are black boxes in which an alphabet is mapped to another alphabet.                            

        BRIEF DESCRIPTION OF CODE:  The user enters the characters of the message in the test bench
                                    along with the setting code for each character which the user has decided and has passed to the receiver.
                                    This data is then encrypted in the following module and then displayed.
                                    Each black box gives the corresponding output based on the mapping done inside it,
                                    The VerilogBM_102_205 module handles the selection of the black box outputs based on the setting input.
                                    It then puts the selected answer from the black box to the output of the machine.
                                    For decrypting the same set of character produced during encoding must be entered with same settings.
                                    
        MODEL: Behavioral                            
*/
 
module VerilogBM_154_233 (output reg [8:1] out, input [8:1] in, input [1:0] setting);

    // Variables for outputs from each black box module
        // variable to store output from black box 1
    wire [8:1] out1;

        // variable to store output from black box 2
    wire [8:1] out2;

        // variable to store output from black box 3
    wire [8:1] out3;

        // variable to store output from black box 4
    wire [8:1] out4;


    // Varible to store inputed ASCII character
    reg [8:1] inp;



    // Black box threads instantiated 
        // black box 1 (output: output bits from box1, input: inp bits from input to the machine)
    block1 box1 (out1, inp);
    
        // black box 1 (output: output bits from box2, input: inp bits from input to the machine)
    block2 box2 (out2, inp);

        // black box 1 (output: output bits from box3, input: inp bits from input to the machine)
    block3 box3 (out3, inp);

        // black box 1 (output: output bits from box4, input: inp bits from input to the machine)
    block4 box4 (out4, inp);
    


    // main thread for selection logic
    always @ (in) begin
        
        // stored input ASCII character in inp 
        inp = in;
        #1;

        // Choosing the black boxes according to the settings. 
        // For example if the setting were 0 then out1 will give the desired output.
        // This output is assigned to the variable out. 
        case (setting)
            2'b00: begin out <= out1; end
            2'b01: begin out <= out2; end
            2'b10: begin out <= out3; end
            2'b11: begin out <= out4; end
        endcase
    end

endmodule

/**
 * Module depicting black box 1 functionality in circuit
 * (output: encoded character for the input, input: input character to the black box)
 */
module block1 (output reg [8:1] out, input [8:1] in);

    // this thread denotes the behavior of the black box:
    // By specifing the mapping of a character to another choosen for this black box
    always @ (in) begin
        case (in)
            "A": begin out <= "O"; end
            "B": begin out <= "X"; end
            "C": begin out <= "Z"; end
            "D": begin out <= "W"; end
            "E": begin out <= "T"; end
            "F": begin out <= "J"; end
            "G": begin out <= "S"; end
            "H": begin out <= "U"; end
            "I": begin out <= "N"; end
            "J": begin out <= "F"; end
            "K": begin out <= "V"; end
            "L": begin out <= "Y"; end
            "M": begin out <= "R"; end
            "N": begin out <= "I"; end
            "O": begin out <= "A"; end
            "P": begin out <= "Q"; end
            "Q": begin out <= "P"; end
            "R": begin out <= "M"; end
            "S": begin out <= "G"; end
            "T": begin out <= "E"; end
            "U": begin out <= "H"; end
            "V": begin out <= "K"; end
            "W": begin out <= "D"; end
            "X": begin out <= "F"; end
            "Y": begin out <= "L"; end
            "Z": begin out <= "C"; end
        endcase
    end

endmodule

/**
 * Module depicting black box 2 functionality in circuit
 * (output: encoded character for the input, input: input character to the black box)
 */
module block2 (output reg [8:1] out, input [8:1] in);

    // this thread denotes the behavior of the black box:
    // By specifing the mapping of a character to another choosen for this black box
    always @ (in) begin
        case (in)
            "A": begin out <= "X"; end
            "B": begin out <= "V"; end
            "C": begin out <= "D"; end
            "D": begin out <= "C"; end
            "E": begin out <= "S"; end
            "F": begin out <= "H"; end
            "G": begin out <= "O"; end
            "H": begin out <= "F"; end
            "I": begin out <= "Y"; end
            "J": begin out <= "T"; end
            "K": begin out <= "W"; end
            "L": begin out <= "Q"; end
            "M": begin out <= "R"; end
            "N": begin out <= "P"; end
            "O": begin out <= "G"; end
            "P": begin out <= "H"; end
            "Q": begin out <= "L"; end
            "R": begin out <= "M"; end
            "S": begin out <= "E"; end
            "T": begin out <= "J"; end
            "U": begin out <= "Z"; end
            "V": begin out <= "F"; end
            "W": begin out <= "K"; end
            "X": begin out <= "A"; end
            "Y": begin out <= "I"; end
            "Z": begin out <= "U"; end
        endcase
    end

endmodule

/**
 * Module depicting black box 3 functionality in circuit
 * (output: encoded character for the input, input: input character to the black box)
 */
module block3 (output reg [8:1] out, input [8:1] in);

    // this thread denotes the behavior of the black box:
    // By specifing the mapping of a character to another choosen for this black box
    always @ (in) begin
        case (in)
            "A": begin out <= "R"; end
            "B": begin out <= "V"; end
            "C": begin out <= "H"; end
            "D": begin out <= "L"; end
            "E": begin out <= "J"; end
            "F": begin out <= "T"; end
            "G": begin out <= "O"; end
            "H": begin out <= "C"; end
            "I": begin out <= "Y"; end
            "J": begin out <= "E"; end
            "K": begin out <= "Q"; end
            "L": begin out <= "D"; end
            "M": begin out <= "Z"; end
            "N": begin out <= "U"; end
            "O": begin out <= "G"; end
            "P": begin out <= "W"; end
            "Q": begin out <= "K"; end
            "R": begin out <= "A"; end
            "S": begin out <= "X"; end
            "T": begin out <= "F"; end
            "U": begin out <= "N"; end
            "V": begin out <= "B"; end
            "W": begin out <= "P"; end
            "X": begin out <= "S"; end
            "Y": begin out <= "I"; end
            "Z": begin out <= "M"; end
        endcase
    end

endmodule

/**
 * Module depicting black box 4 functionality in circuit
 * (output: encoded character for the input, input: input character to the black box)
 */
module block4 (output reg [8:1] out, input [8:1] in);

    // this thread denotes the behavior of the black box:
    // By specifing the mapping of a character to another choosen for this black box
    always @ (in) begin
        case (in)
            "A": begin out <= "F"; end
            "B": begin out <= "Y"; end
            "C": begin out <= "M"; end
            "D": begin out <= "S"; end
            "E": begin out <= "J"; end
            "F": begin out <= "A"; end
            "G": begin out <= "N"; end
            "H": begin out <= "R"; end
            "I": begin out <= "V"; end
            "J": begin out <= "E"; end
            "K": begin out <= "T"; end
            "L": begin out <= "Q"; end
            "M": begin out <= "C"; end
            "N": begin out <= "G"; end
            "O": begin out <= "X"; end
            "P": begin out <= "U"; end
            "Q": begin out <= "L"; end
            "R": begin out <= "H"; end
            "S": begin out <= "D"; end
            "T": begin out <= "K"; end
            "U": begin out <= "P"; end
            "V": begin out <= "I"; end
            "W": begin out <= "Z"; end
            "X": begin out <= "O"; end
            "Y": begin out <= "B"; end
            "Z": begin out <= "W"; end
        endcase
    end

endmodule

Verilog-154-233/Behavioral/Verilog-154-233.v
`timescale 1ns/100ps

// TEST BENCH

/*
        TITLE: THE MODIFIED ENIGMA MACHINE

        REG NO: 16CO154-16CO233

        ABSTRACT: A circuit that encrypts data by mapping each alphabet to another alphabet randomly. 
                  This will be done in such a way that if the same alphabet is repeated, 
                  the encrypted alphabet will not be the same always.

        FUNCTIONALITIES: The following modules are present

                            a) Encoder: It is an alphabet to binary encoder
                            b) Decoder: It is a binary to alphabet decoder
                            
                            There is an input array- setting, which helps in deciding which block must encode/decode data
                            
                            c) Block 1,2,3 and 4: Blocks which encode/decode data using boolean equations

        BRIEF DESCRIPTION OF CODE:  The user enters some data (given in test-bench) and sets a code to encrypt the data.
                                    This data is then encrypted in the following module and then displayed.
                                    For decrypting the same data must be entered with same settings.
                                    For making the process easier there is an alphabet-binary encoder along with a binary-alphabet decoder.
*/

module Verilog_154_233;

    reg [1:0] setting;
    reg [8:1] in;
    wire [8:1] out;

    
    VerilogBM_154_233 inst(out, in, setting);
    
	// input combinations 
    initial begin

        $dumpfile("VerilogBM-154-233.vcd");
        $dumpvars(0, Verilog_154_233);

        $display("\n\n ================== THE MODIFIED ENIGMA MACHINE ==================\n");
        $display("\n\t------ ENCRYPTING: \"HELLOWORLD\", SETTINGS: 2103 ------\n");

        setting = 2'b10;
        in = "H";
        #10;
        setting = 2'b01;
        in = "E";
        #10;
        setting = 2'b00;
        in = "L";
        #10;
        setting = 2'b11;
        in = "L";
        #10;
        setting = 2'b10;
        in = "O";
        #10;
        setting = 2'b01;
        in = "W";
        #10;
        setting = 2'b00;
        in = "O";
        #10;
        setting = 2'b11;
        in = "R";
        #10;
        setting = 2'b10;
        in = "L";
        #10;
        setting = 2'b01;
        in = "D";
        #10;

        $display("\n\t------ DECRYPTING: \"CSYQGKAHDC\", SETTINGS: 2103 ------\n");

        #10;
        setting = 2'b10;
        in = "C";
        #10;
        setting = 2'b01;
        in = "S";
        #10;
        setting = 2'b00;
        in = "Y";
        #10;
        setting = 2'b11;
        in = "Q";
        #10;
        setting = 2'b10;
        in = "G";
        #10;
        setting = 2'b01;
        in = "K";
        #10;
        setting = 2'b00;
        in = "A";
        #10;
        setting = 2'b11;
        in = "H";
        #10;
        setting = 2'b10;
        in = "D";
        #10;
        setting = 2'b01;
        in = "C";
        #10;
    end

	// display outputs
    always @ (in) begin
        #5;
        $display("\n\t\tinput: %c output: %c\n", in, out);
    end

endmodule

Verilog-154-233/Behavioral/VerilogBM-154-233.vcd
$date
	Tue Nov  7 19:57:09 2017
$end
$version
	Icarus Verilog
$end
$timescale
	100ps
$end
$scope module Verilog_154_233 $end
$var wire 8 ! out [8:1] $end
$var reg 8 " in [8:1] $end
$var reg 2 # setting [1:0] $end
$scope module inst $end
$var wire 8 $ in [8:1] $end
$var wire 8 % out1 [8:1] $end
$var wire 8 & out2 [8:1] $end
$var wire 8 ' out3 [8:1] $end
$var wire 8 ( out4 [8:1] $end
$var wire 2 ) setting [1:0] $end
$var reg 8 * inp [8:1] $end
$var reg 8 + out [8:1] $end
$scope module box1 $end
$var wire 8 , in [8:1] $end
$var reg 8 - out [8:1] $end
$upscope $end
$scope module box2 $end
$var wire 8 . in [8:1] $end
$var reg 8 / out [8:1] $end
$upscope $end
$scope module box3 $end
$var wire 8 0 in [8:1] $end
$var reg 8 1 out [8:1] $end
$upscope $end
$scope module box4 $end
$var wire 8 2 in [8:1] $end
$var reg 8 3 out [8:1] $end
$upscope $end
$upscope $end
$upscope $end
$enddefinitions $end
#0
$dumpvars
b1010010 3
b1001000 2
b1000011 1
b1001000 0
b1000110 /
b1001000 .
b1010101 -
b1001000 ,
bx +
b1001000 *
b10 )
b1010010 (
b1000011 '
b1000110 &
b1010101 %
b1001000 $
b10 #
b1001000 "
bx !
$end
#10
b1000011 +
b1000011 !
#100
b1010100 -
b1010100 %
b1010011 /
b1010011 &
b1001010 1
b1001010 '
b1001010 3
b1001010 (
b1000101 *
b1000101 ,
b1000101 .
b1000101 0
b1000101 2
b1000101 "
b1000101 $
b1 #
b1 )
#110
b1010011 +
b1010011 !
#200
b1010001 3
b1010001 (
b1000100 1
b1000100 '
b1010001 /
b1010001 &
b1011001 -
b1011001 %
b1001100 *
b1001100 ,
b1001100 .
b1001100 0
b1001100 2
b1001100 "
b1001100 $
b0 #
b0 )
#210
b1011001 +
b1011001 !
#300
b11 #
b11 )
#400
b1000001 -
b1000001 %
b1000111 /
b1000111 &
b1000111 1
b1000111 '
b1011000 3
b1011000 (
b1001111 *
b1001111 ,
b1001111 .
b1001111 0
b1001111 2
b1001111 "
b1001111 $
b10 #
b10 )
#410
b1000111 +
b1000111 !
#500
b1011010 3
b1011010 (
b1010000 1
b1010000 '
b1001011 /
b1001011 &
b1000100 -
b1000100 %
b1010111 *
b1010111 ,
b1010111 .
b1010111 0
b1010111 2
b1010111 "
b1010111 $
b1 #
b1 )
#510
b1001011 +
b1001011 !
#600
b1000001 -
b1000001 %
b1000111 /
b1000111 &
b1000111 1
b1000111 '
b1011000 3
b1011000 (
b1001111 *
b1001111 ,
b1001111 .
b1001111 0
b1001111 2
b1001111 "
b1001111 $
b0 #
b0 )
#610
b1000001 +
b1000001 !
#700
b1001000 3
b1001000 (
b1000001 1
b1000001 '
b1001101 /
b1001101 &
b1001101 -
b1001101 %
b1010010 *
b1010010 ,
b1010010 .
b1010010 0
b1010010 2
b1010010 "
b1010010 $
b11 #
b11 )
#710
b1001000 +
b1001000 !
#800
b1011001 -
b1011001 %
b1010001 /
b1010001 &
b1000100 1
b1000100 '
b1010001 3
b1010001 (
b1001100 *
b1001100 ,
b1001100 .
b1001100 0
b1001100 2
b1001100 "
b1001100 $
b10 #
b10 )
#810
b1000100 +
b1000100 !
#900
b1010011 3
b1010011 (
b1001100 1
b1001100 '
b1000011 /
b1000011 &
b1010111 -
b1010111 %
b1000100 *
b1000100 ,
b1000100 .
b1000100 0
b1000100 2
b1000100 "
b1000100 $
b1 #
b1 )
#910
b1000011 +
b1000011 !
#1100
b1011010 -
b1011010 %
b1000100 /
b1000100 &
b1001000 1
b1001000 '
b1001101 3
b1001101 (
b1000011 *
b1000011 ,
b1000011 .
b1000011 0
b1000011 2
b1000011 "
b1000011 $
b10 #
b10 )
#1110
b1001000 +
b1001000 !
#1200
b1000100 3
b1000100 (
b1011000 1
b1011000 '
b1000101 /
b1000101 &
b1000111 -
b1000111 %
b1010011 *
b1010011 ,
b1010011 .
b1010011 0
b1010011 2
b1010011 "
b1010011 $
b1 #
b1 )
#1210
b1000101 +
b1000101 !
#1300
b1001100 -
b1001100 %
b1001001 /
b1001001 &
b1001001 1
b1001001 '
b1000010 3
b1000010 (
b1011001 *
b1011001 ,
b1011001 .
b1011001 0
b1011001 2
b1011001 "
b1011001 $
b0 #
b0 )
#1310
b1001100 +
b1001100 !
#1400
b1001100 3
b1001100 (
b1001011 1
b1001011 '
b1001100 /
b1001100 &
b1010000 -
b1010000 %
b1010001 *
b1010001 ,
b1010001 .
b1010001 0
b1010001 2
b1010001 "
b1010001 $
b11 #
b11 )
#1500
b1010011 -
b1010011 %
b1001111 /
b1001111 &
b1001111 1
b1001111 '
b1001110 3
b1001110 (
b1000111 *
b1000111 ,
b1000111 .
b1000111 0
b1000111 2
b1000111 "
b1000111 $
b10 #
b10 )
#1510
b1001111 +
b1001111 !
#1600
b1010100 3
b1010100 (
b1010001 1
b1010001 '
b1010111 /
b1010111 &
b1010110 -
b1010110 %
b1001011 *
b1001011 ,
b1001011 .
b1001011 0
b1001011 2
b1001011 "
b1001011 $
b1 #
b1 )
#1610
b1010111 +
b1010111 !
#1700
b1001111 -
b1001111 %
b1011000 /
b1011000 &
b1010010 1
b1010010 '
b1000110 3
b1000110 (
b1000001 *
b1000001 ,
b1000001 .
b1000001 0
b1000001 2
b1000001 "
b1000001 $
b0 #
b0 )
#1710
b1001111 +
b1001111 !
#1800
b1010010 3
b1010010 (
b1000011 1
b1000011 '
b1000110 /
b1000110 &
b1010101 -
b1010101 %
b1001000 *
b1001000 ,
b1001000 .
b1001000 0
b1001000 2
b1001000 "
b1001000 $
b11 #
b11 )
#1810
b1010010 +
b1010010 !
#1900
b1010111 -
b1010111 %
b1000011 /
b1000011 &
b1001100 1
b1001100 '
b1010011 3
b1010011 (
b1000100 *
b1000100 ,
b1000100 .
b1000100 0
b1000100 2
b1000100 "
b1000100 $
b10 #
b10 )
#1910
b1001100 +
b1001100 !
#2000
b1001101 3
b1001101 (
b1001000 1
b1001000 '
b1000100 /
b1000100 &
b1011010 -
b1011010 %
b1000011 *
b1000011 ,
b1000011 .
b1000011 0
b1000011 2
b1000011 "
b1000011 $
b1 #
b1 )
#2010
b1000100 +
b1000100 !
